task4_with_timer/f1fsm.sv
module f1fsm(
    input logic clk,
    input logic en, 
    input logic rst,
    input logic trigger,
    output logic [7:0] dout,
    output logic cmd_delay,
    output logic cmd_seq
);

    logic [7:0] num = 8'b0;
    
    typedef enum {IDLE, S0, S1, S2, S3, S4, S5, S6, S7} light_state;
    light_state current_state, next_state;


    always_ff @(posedge clk) begin
        if (rst) current_state <= IDLE;
        
        if (current_state == IDLE) begin
            if (trigger) current_state <= next_state;
        end
        
        else begin
            if (en) current_state <= next_state;
            else current_state <= current_state;
        end

    end

    always_comb begin
        case (current_state)
        IDLE:   next_state = S0;
        S0:     next_state = S1;
        S1:     next_state = S2;
        S2:     next_state = S3;     
        S3:     next_state = S4;
        S4:     next_state = S5;
        S5:     next_state = S6;
        S6:     next_state = S7;
        S7:     next_state = IDLE;        
        endcase    
    end

    always_comb begin
        case(current_state)
                IDLE:   begin 
                        num = 8'b0;
                        cmd_delay = 1'b0;
                        cmd_seq = 1'b0;
                end
                
                S0:     begin 
                        num = 8'b1;
                        cmd_seq = 1'b1;
                end
                S1:     num = 8'b11;     
                S2:     num = 8'b111;     
                S3:     num = 8'b1111;
                S4:     num = 8'b11111;
                S5:     num = 8'b111111;
                S6:     num = 8'b1111111;
                S7:     begin
                        num = 8'b11111111;
                        cmd_delay = 1'b1;
                        cmd_seq = 1'b0;
                end
        endcase
    end

    assign dout = num;

endmodule

task4/delay.sv
module delay #(
	parameter WIDTH = 10    // no of bits in delay counter
)(
    input   logic               clk,        // clock signal
    input   logic               rst,        // reset signal
    input   logic               trigger,    // trigger input signal
    input   logic [WIDTH-1:0]   n,          // no of clock cycle delay
    output  logic               time_out    // output pulse signal
);
    // Declare counter
    logic [WIDTH-1:0]   count = {WIDTH{1'b0}};            // internal counter

    // Define our states
    typedef enum {IDLE, COUNTING, TIME_OUT, WAIT_LOW}  my_state;
    my_state current_state, next_state;

    // counter
    always_ff @(posedge clk)
        if (rst | trigger | count=={WIDTH{1'b0}}) count <= n - 1'b1;
        else                                count <= count - 1'b1;

    // state transition
    always_ff @(posedge clk)
        if (rst)    current_state <= IDLE;
        else        current_state <= next_state; 

    // next state logic
    always_comb
        case (current_state)
            IDLE:       if (trigger==1'b1)  next_state = COUNTING;
                        else    next_state = current_state;
            COUNTING:   if (count=={WIDTH{1'b0}}) next_state = TIME_OUT;
                        else    next_state = current_state;
            TIME_OUT:   if (trigger==1'b1)  next_state = WAIT_LOW;
                        else    next_state = IDLE;
            WAIT_LOW:   if (trigger==1'b0)  next_state = IDLE;
                        else    next_state = current_state;
            default: next_state = IDLE;
        endcase
    
    // output logic
    always_comb
        case (current_state)
            IDLE:       time_out = 1'b0;
            COUNTING:   time_out = 1'b0;
            TIME_OUT:   time_out = 1'b1;
            WAIT_LOW:   time_out = 1'b0;
            default:    time_out = 1'b0;
        endcase
endmodule

task4_with_timer/lfsr.sv
module lfsr(
    input logic rst,
    input logic en,
    input logic clk,
    output logic [7:0] dout 
);

    logic [7:0] sreg = 8'b1;
    
    assign dout = sreg;

    always_ff @(posedge clk) begin
        if (rst)
            sreg <= 8'b1;
        
        else if(en)
            sreg <= {sreg[6:0], sreg[7] ^ sreg[6] ^ sreg[1] ^ sreg[0]};
    
    end

endmodule

task4_with_timer/clktick.sv
module clktick #(
	parameter WIDTH = 8
)(
  // interface signals
  input  logic             clk,      // clock 
  input  logic             rst,      // reset
  input  logic             en,       // enable signal
  input  logic [WIDTH-1:0] N,     	 // clock divided by N+1
  output logic  		       tick      // tick output
);

logic [WIDTH-1:0] count;

always_ff @ (posedge clk)
    if (rst) begin
        tick <= 1'b0;
        count <= N;  
        end
    else if (en) begin
	    if (count == 0) begin
		    tick <= 1'b1;
		    count <= N;
	        end
	    else begin
		    tick <= 1'b0;
		    count <= count - 1'b1;
	        end
        end
endmodule

task4_with_timer/top.sv
module top #(
    parameter WIDTH = 8
) (
    input logic clk,
    input logic en, 
    input logic rst,
    input logic [WIDTH-1:0] N,
    input logic trigger,
    output logic [7:0] dout,
    output logic cmd_seq,
    output logic cmd_delay,
    output logic [WIDTH-1:0] n
);

logic delay;
logic mtick;
logic muxout;
assign muxout = cmd_seq ? mtick : delay;


clktick clktickr(
    .clk(clk),
    .en(cmd_seq),
    .N(N),
    .rst(rst),
    .tick(mtick)//output
);

lfsr randomdelayer(
    .clk(clk),
    .en(en),
    .rst(rst),
    .dout(n) //output
);

delay delayer(
    .n(n),
    .clk(clk),
    .rst(rst),
    .trigger(cmd_delay),
    .time_out(delay) //output
);

f1fsm f1fsm(
    .en(muxout),
    .clk(clk),
    .rst(rst),
    .trigger(trigger),
    .dout(dout),
    .cmd_delay(cmd_delay),
    .cmd_seq(cmd_seq)
);

  
endmodule

task4_with_timer/top.vcd
$version Generated by VerilatedVcd $end
$date Wed Nov 16 16:21:54 2022 $end
$timescale 1ps $end

 $scope module TOP $end
  $var wire  8 / N [7:0] $end
  $var wire  1 , clk $end
  $var wire  1 3 cmd_delay $end
  $var wire  1 2 cmd_seq $end
  $var wire  8 1 dout [7:0] $end
  $var wire  1 - en $end
  $var wire  8 4 n [7:0] $end
  $var wire  1 . rst $end
  $var wire  1 0 trigger $end
  $scope module top $end
   $var wire  8 / N [7:0] $end
   $var wire 32 7 WIDTH [31:0] $end
   $var wire  1 , clk $end
   $var wire  1 3 cmd_delay $end
   $var wire  1 2 cmd_seq $end
   $var wire  1 # delay $end
   $var wire  8 1 dout [7:0] $end
   $var wire  1 - en $end
   $var wire  1 $ mtick $end
   $var wire  1 5 muxout $end
   $var wire  8 4 n [7:0] $end
   $var wire  1 . rst $end
   $var wire  1 0 trigger $end
   $scope module clktickr $end
    $var wire  8 / N [7:0] $end
    $var wire 32 7 WIDTH [31:0] $end
    $var wire  1 , clk $end
    $var wire  8 % count [7:0] $end
    $var wire  1 2 en $end
    $var wire  1 . rst $end
    $var wire  1 $ tick $end
   $upscope $end
   $scope module delayer $end
    $var wire 32 7 WIDTH [31:0] $end
    $var wire  1 , clk $end
    $var wire  8 & count [7:0] $end
    $var wire 32 ' current_state [31:0] $end
    $var wire  8 4 n [7:0] $end
    $var wire 32 6 next_state [31:0] $end
    $var wire  1 . rst $end
    $var wire  1 # time_out $end
    $var wire  1 3 trigger $end
   $upscope $end
   $scope module f1fsm $end
    $var wire  1 , clk $end
    $var wire  1 3 cmd_delay $end
    $var wire  1 2 cmd_seq $end
    $var wire 32 ) current_state [31:0] $end
    $var wire  8 1 dout [7:0] $end
    $var wire  1 5 en $end
    $var wire 32 * next_state [31:0] $end
    $var wire  8 ( num [7:0] $end
    $var wire  1 . rst $end
    $var wire  1 0 trigger $end
   $upscope $end
   $scope module randomdelayer $end
    $var wire  1 , clk $end
    $var wire  8 4 dout [7:0] $end
    $var wire  1 - en $end
    $var wire  1 . rst $end
    $var wire  8 + sreg [7:0] $end
   $upscope $end
  $upscope $end
 $upscope $end
$enddefinitions $end


#0
0#
0$
b00000000 %
b00000000 &
b00000000000000000000000000000000 '
b00000000 (
b00000000000000000000000000000000 )
b00000000000000000000000000000000 *
b00000000 +
1,
0-
0.
b00010110 /
00
b00000000 1
02
03
b00000000 4
05
b00000000000000000000000000000000 6
b00000000000000000000000000001000 7
#1
b00000000000000000000000000000001 *
b00000001 +
0,
b00000001 4
#2
1,
1.
#3
0,
#4
b00010110 %
1,
#5
0,
#6
1,
0.
#7
0,
#8
1,
1-
#9
0,
#10
b00000011 +
1,
b00000011 4
#11
0,
#12
b00000010 &
b00000110 +
1,
b00000110 4
#13
0,
#14
b00000001 &
b00001101 +
1,
b00001101 4
#15
0,
#16
b00000000 &
b00011011 +
1,
b00011011 4
#17
0,
#18
b00011010 &
b00110110 +
1,
b00110110 4
#19
0,
#20
b00011001 &
b01101101 +
1,
b01101101 4
#21
0,
#22
b00011000 &
b11011010 +
1,
b11011010 4
#23
0,
#24
b00010111 &
b10110101 +
1,
b10110101 4
#25
0,
#26
b00010110 &
b01101010 +
1,
b01101010 4
#27
0,
#28
b00010101 &
b11010100 +
1,
b11010100 4
#29
0,
#30
b00010100 &
b10101000 +
1,
b10101000 4
#31
0,
#32
b00010011 &
b01010001 +
1,
b01010001 4
#33
0,
#34
b00010010 &
b10100010 +
1,
b10100010 4
#35
0,
#36
b00010001 &
b01000100 +
1,
b01000100 4
#37
0,
#38
b00010000 &
b10001001 +
1,
b10001001 4
#39
0,
#40
b00001111 &
b00010010 +
1,
b00010010 4
#41
0,
#42
b00001110 &
b00100101 +
1,
b00100101 4
#43
0,
#44
b00001101 &
b01001011 +
1,
b01001011 4
#45
0,
#46
b00001100 &
b10010111 +
1,
b10010111 4
#47
0,
#48
b00001011 &
b00101111 +
1,
b00101111 4
#49
0,
#50
b00001010 &
b01011110 +
1,
b01011110 4
#51
0,
#52
b00001001 &
b10111100 +
1,
b10111100 4
#53
0,
#54
b00001000 &
b01111001 +
1,
b01111001 4
#55
0,
#56
b00000111 &
b11110010 +
1,
b11110010 4
#57
0,
#58
b00000110 &
b11100101 +
1,
b11100101 4
#59
0,
#60
b00000101 &
b11001011 +
1,
b11001011 4
#61
0,
#62
b00000100 &
b10010110 +
1,
b10010110 4
#63
0,
#64
b00000011 &
b00101100 +
1,
b00101100 4
#65
0,
#66
b00000010 &
b01011000 +
1,
b01011000 4
#67
0,
#68
b00000001 &
b10110001 +
1,
b10110001 4
#69
0,
#70
b00000000 &
b01100010 +
1,
b01100010 4
#71
0,
#72
b01100001 &
b11000100 +
1,
b11000100 4
#73
0,
#74
b01100000 &
b10001000 +
1,
b10001000 4
#75
0,
#76
b01011111 &
b00010001 +
1,
b00010001 4
#77
0,
#78
b01011110 &
b00100011 +
1,
b00100011 4
#79
0,
#80
b01011101 &
b01000110 +
1,
b01000110 4
#81
0,
#82
b01011100 &
b10001100 +
1,
b10001100 4
#83
0,
#84
b01011011 &
b00011001 +
1,
b00011001 4
#85
0,
#86
b01011010 &
b00110011 +
1,
b00110011 4
#87
0,
#88
b01011001 &
b01100110 +
1,
b01100110 4
#89
0,
#90
b01011000 &
b11001100 +
1,
b11001100 4
#91
0,
#92
b01010111 &
b10011000 +
1,
b10011000 4
#93
0,
#94
b01010110 &
b00110001 +
1,
b00110001 4
#95
0,
#96
b01010101 &
b01100011 +
1,
b01100011 4
#97
0,
#98
b01010100 &
b11000111 +
1,
b11000111 4
#99
0,
#100
b01010011 &
b10001110 +
1,
b10001110 4
#101
0,
#102
b01010010 &
b00011100 +
1,
b00011100 4
#103
0,
#104
b01010001 &
b00111000 +
1,
b00111000 4
#105
0,
#106
b01010000 &
b01110000 +
1,
b01110000 4
#107
0,
#108
b01001111 &
b11100001 +
1,
b11100001 4
#109
0,
#110
b01001110 &
b11000011 +
1,
b11000011 4
#111
0,
#112
b01001101 &
b10000110 +
1,
b10000110 4
#113
0,
#114
b01001100 &
b00001100 +
1,
b00001100 4
#115
0,
#116
b01001011 &
b00011000 +
1,
b00011000 4
#117
0,
#118
b01001010 &
b00110000 +
1,
b00110000 4
#119
0,
#120
b01001001 &
b01100000 +
1,
b01100000 4
#121
0,
#122
b01001000 &
b11000001 +
1,
b11000001 4
#123
0,
#124
b01000111 &
b10000011 +
1,
b10000011 4
#125
0,
#126
b01000110 &
b00000111 +
1,
b00000111 4
#127
0,
#128
b01000101 &
b00001110 +
1,
b00001110 4
#129
0,
#130
b01000100 &
b00011101 +
1,
b00011101 4
#131
0,
#132
b01000011 &
b00111011 +
1,
b00111011 4
#133
0,
#134
b01000010 &
b01110110 +
1,
b01110110 4
#135
0,
#136
b01000001 &
b11101100 +
1,
b11101100 4
#137
0,
#138
b01000000 &
b11011000 +
1,
b11011000 4
#139
0,
#140
b00111111 &
b10110000 +
1,
b10110000 4
#141
0,
#142
b00111110 &
b01100001 +
1,
b01100001 4
#143
0,
#144
b00111101 &
b11000010 +
1,
b11000010 4
#145
0,
#146
b00111100 &
b10000101 +
1,
b10000101 4
#147
0,
#148
b00111011 &
b00001010 +
1,
b00001010 4
#149
0,
#150
b00111010 &
b00010101 +
1,
b00010101 4
#151
0,
#152
b00111001 &
b00101011 +
1,
b00101011 4
#153
0,
#154
b00111000 &
b01010110 +
1,
b01010110 4
#155
0,
#156
b00110111 &
b10101100 +
1,
b10101100 4
#157
0,
#158
b00110110 &
b01011001 +
1,
b01011001 4
#159
0,
#160
b00110101 &
b10110010 +
1,
b10110010 4
#161
0,
#162
b00110100 &
b01100100 +
1,
b01100100 4
#163
0,
#164
b00110011 &
b11001001 +
1,
b11001001 4
#165
0,
#166
b00110010 &
b10010011 +
1,
10
b10010011 4
#167
0,
#168
b00110001 &
b00000001 (
b00000000000000000000000000000001 )
b00000000000000000000000000000010 *
b00100111 +
1,
00
b00000001 1
12
b00100111 4
#169
0,
#170
b00010101 %
b00110000 &
b01001110 +
1,
b01001110 4
#171
0,
#172
b00010100 %
b00101111 &
b10011100 +
1,
b10011100 4
#173
0,
#174
b00010011 %
b00101110 &
b00111001 +
1,
b00111001 4
#175
0,
#176
b00010010 %
b00101101 &
b01110011 +
1,
b01110011 4
#177
0,
#178
b00010001 %
b00101100 &
b11100111 +
1,
b11100111 4
#179
0,
#180
b00010000 %
b00101011 &
b11001110 +
1,
b11001110 4
#181
0,
#182
b00001111 %
b00101010 &
b10011101 +
1,
b10011101 4
#183
0,
#184
b00001110 %
b00101001 &
b00111010 +
1,
b00111010 4
#185
0,
#186
b00001101 %
b00101000 &
b01110101 +
1,
b01110101 4
#187
0,
#188
b00001100 %
b00100111 &
b11101010 +
1,
b11101010 4
#189
0,
#190
b00001011 %
b00100110 &
b11010101 +
1,
b11010101 4
#191
0,
#192
b00001010 %
b00100101 &
b10101011 +
1,
b10101011 4
#193
0,
#194
b00001001 %
b00100100 &
b01010111 +
1,
b01010111 4
#195
0,
#196
b00001000 %
b00100011 &
b10101111 +
1,
b10101111 4
#197
0,
#198
b00000111 %
b00100010 &
b01011111 +
1,
b01011111 4
#199
0,
#200
b00000110 %
b00100001 &
b10111111 +
1,
b10111111 4
#201
0,
#202
b00000101 %
b00100000 &
b01111111 +
1,
b01111111 4
#203
0,
#204
b00000100 %
b00011111 &
b11111111 +
1,
b11111111 4
#205
0,
#206
b00000011 %
b00011110 &
b11111110 +
1,
b11111110 4
#207
0,
#208
b00000010 %
b00011101 &
b11111101 +
1,
b11111101 4
#209
0,
#210
b00000001 %
b00011100 &
b11111011 +
1,
b11111011 4
#211
0,
#212
b00000000 %
b00011011 &
b11110110 +
1,
b11110110 4
#213
0,
#214
1$
b00010110 %
b00011010 &
b11101101 +
1,
b11101101 4
15
#215
0,
#216
0$
b00010101 %
b00011001 &
b00000011 (
b00000000000000000000000000000010 )
b00000000000000000000000000000011 *
b11011011 +
1,
b00000011 1
b11011011 4
05
#217
0,
#218
b00010100 %
b00011000 &
b10110110 +
1,
b10110110 4
#219
0,
#220
b00010011 %
b00010111 &
b01101100 +
1,
b01101100 4
#221
0,
#222
b00010010 %
b00010110 &
b11011001 +
1,
b11011001 4
#223
0,
#224
b00010001 %
b00010101 &
b10110011 +
1,
b10110011 4
#225
0,
#226
b00010000 %
b00010100 &
b01100111 +
1,
b01100111 4
#227
0,
#228
b00001111 %
b00010011 &
b11001111 +
1,
b11001111 4
#229
0,
#230
b00001110 %
b00010010 &
b10011110 +
1,
b10011110 4
#231
0,
#232
b00001101 %
b00010001 &
b00111100 +
1,
b00111100 4
#233
0,
#234
b00001100 %
b00010000 &
b01111000 +
1,
b01111000 4
#235
0,
#236
b00001011 %
b00001111 &
b11110001 +
1,
b11110001 4
#237
0,
#238
b00001010 %
b00001110 &
b11100011 +
1,
b11100011 4
#239
0,
#240
b00001001 %
b00001101 &
b11000110 +
1,
b11000110 4
#241
0,
#242
b00001000 %
b00001100 &
b10001101 +
1,
b10001101 4
#243
0,
#244
b00000111 %
b00001011 &
b00011010 +
1,
b00011010 4
#245
0,
#246
b00000110 %
b00001010 &
b00110101 +
1,
b00110101 4
#247
0,
#248
b00000101 %
b00001001 &
b01101011 +
1,
b01101011 4
#249
0,
#250
b00000100 %
b00001000 &
b11010111 +
1,
b11010111 4
#251
0,
#252
b00000011 %
b00000111 &
b10101110 +
1,
b10101110 4
#253
0,
#254
b00000010 %
b00000110 &
b01011100 +
1,
b01011100 4
#255
0,
#256
b00000001 %
b00000101 &
b10111001 +
1,
b10111001 4
#257
0,
#258
b00000000 %
b00000100 &
b01110010 +
1,
b01110010 4
#259
0,
#260
1$
b00010110 %
b00000011 &
b11100100 +
1,
b11100100 4
15
#261
0,
#262
0$
b00010101 %
b00000010 &
b00000111 (
b00000000000000000000000000000011 )
b00000000000000000000000000000100 *
b11001000 +
1,
b00000111 1
b11001000 4
05
#263
0,
#264
b00010100 %
b00000001 &
b10010000 +
1,
b10010000 4
#265
0,
#266
b00010011 %
b00000000 &
b00100001 +
1,
b00100001 4
#267
0,
#268
b00010010 %
b00100000 &
b01000011 +
1,
b01000011 4
#269
0,
#270
b00010001 %
b00011111 &
b10000111 +
1,
b10000111 4
#271
0,
#272
b00010000 %
b00011110 &
b00001111 +
1,
b00001111 4
#273
0,
#274
b00001111 %
b00011101 &
b00011110 +
1,
b00011110 4
#275
0,
#276
b00001110 %
b00011100 &
b00111101 +
1,
b00111101 4
#277
0,
#278
b00001101 %
b00011011 &
b01111011 +
1,
b01111011 4
#279
0,
#280
b00001100 %
b00011010 &
b11110111 +
1,
b11110111 4
#281
0,
#282
b00001011 %
b00011001 &
b11101110 +
1,
b11101110 4
#283
0,
#284
b00001010 %
b00011000 &
b11011101 +
1,
b11011101 4
#285
0,
#286
b00001001 %
b00010111 &
b10111011 +
1,
b10111011 4
#287
0,
#288
b00001000 %
b00010110 &
b01110111 +
1,
b01110111 4
#289
0,
#290
b00000111 %
b00010101 &
b11101111 +
1,
b11101111 4
#291
0,
#292
b00000110 %
b00010100 &
b11011110 +
1,
b11011110 4
#293
0,
#294
b00000101 %
b00010011 &
b10111101 +
1,
b10111101 4
#295
0,
#296
b00000100 %
b00010010 &
b01111010 +
1,
b01111010 4
#297
0,
#298
b00000011 %
b00010001 &
b11110100 +
1,
b11110100 4
#299
0,
#300
b00000010 %
b00010000 &
b11101000 +
1,
b11101000 4
#301
0,
#302
b00000001 %
b00001111 &
b11010000 +
1,
b11010000 4
#303
0,
#304
b00000000 %
b00001110 &
b10100000 +
1,
b10100000 4
#305
0,
#306
1$
b00010110 %
b00001101 &
b01000001 +
1,
b01000001 4
15
#307
0,
#308
0$
b00010101 %
b00001100 &
b00001111 (
b00000000000000000000000000000100 )
b00000000000000000000000000000101 *
b10000010 +
1,
b00001111 1
b10000010 4
05
#309
0,
#310
b00010100 %
b00001011 &
b00000100 +
1,
b00000100 4
#311
0,
#312
b00010011 %
b00001010 &
b00001000 +
1,
b00001000 4
#313
0,
#314
b00010010 %
b00001001 &
b00010000 +
1,
b00010000 4
#315
0,
#316
b00010001 %
b00001000 &
b00100000 +
1,
b00100000 4
#317
0,
#318
b00010000 %
b00000111 &
b01000000 +
1,
b01000000 4
#319
0,
#320
b00001111 %
b00000110 &
b10000001 +
1,
b10000001 4
#321
0,
#322
b00001110 %
b00000101 &
b00000010 +
1,
b00000010 4
#323
0,
#324
b00001101 %
b00000100 &
b00000101 +
1,
b00000101 4
#325
0,
#326
b00001100 %
b00000011 &
b00001011 +
1,
b00001011 4
#327
0,
#328
b00001011 %
b00000010 &
b00010110 +
1,
b00010110 4
#329
0,
#330
b00001010 %
b00000001 &
b00101101 +
1,
b00101101 4
#331
0,
#332
b00001001 %
b00000000 &
b01011011 +
1,
b01011011 4
#333
0,
#334
b00001000 %
b01011010 &
b10110111 +
1,
b10110111 4
#335
0,
#336
b00000111 %
b01011001 &
b01101111 +
1,
b01101111 4
#337
0,
#338
b00000110 %
b01011000 &
b11011111 +
1,
b11011111 4
#339
0,
#340
b00000101 %
b01010111 &
b10111110 +
1,
b10111110 4
#341
0,
#342
b00000100 %
b01010110 &
b01111100 +
1,
b01111100 4
#343
0,
#344
b00000011 %
b01010101 &
b11111001 +
1,
b11111001 4
#345
0,
#346
b00000010 %
b01010100 &
b11110011 +
1,
b11110011 4
#347
0,
#348
b00000001 %
b01010011 &
b11100110 +
1,
b11100110 4
#349
0,
#350
b00000000 %
b01010010 &
b11001101 +
1,
b11001101 4
#351
0,
#352
1$
b00010110 %
b01010001 &
b10011011 +
1,
b10011011 4
15
#353
0,
#354
0$
b00010101 %
b01010000 &
b00011111 (
b00000000000000000000000000000101 )
b00000000000000000000000000000110 *
b00110111 +
1,
b00011111 1
b00110111 4
05
#355
0,
#356
b00010100 %
b01001111 &
b01101110 +
1,
b01101110 4
#357
0,
#358
b00010011 %
b01001110 &
b11011100 +
1,
b11011100 4
#359
0,
#360
b00010010 %
b01001101 &
b10111000 +
1,
b10111000 4
#361
0,
#362
b00010001 %
b01001100 &
b01110001 +
1,
b01110001 4
#363
0,
#364
b00010000 %
b01001011 &
b11100010 +
1,
b11100010 4
#365
0,
#366
b00001111 %
b01001010 &
b11000101 +
1,
b11000101 4
#367
0,
#368
b00001110 %
b01001001 &
b10001011 +
1,
b10001011 4
#369
0,
#370
b00001101 %
b01001000 &
b00010111 +
1,
b00010111 4
#371
0,
#372
b00001100 %
b01000111 &
b00101110 +
1,
b00101110 4
#373
0,
#374
b00001011 %
b01000110 &
b01011101 +
1,
b01011101 4
#375
0,
#376
b00001010 %
b01000101 &
b10111010 +
1,
b10111010 4
#377
0,
#378
b00001001 %
b01000100 &
b01110100 +
1,
b01110100 4
#379
0,
#380
b00001000 %
b01000011 &
b11101001 +
1,
b11101001 4
#381
0,
#382
b00000111 %
b01000010 &
b11010011 +
1,
b11010011 4
#383
0,
#384
b00000110 %
b01000001 &
b10100110 +
1,
b10100110 4
#385
0,
#386
b00000101 %
b01000000 &
b01001100 +
1,
b01001100 4
#387
0,
#388
b00000100 %
b00111111 &
b10011001 +
1,
b10011001 4
#389
0,
#390
b00000011 %
b00111110 &
b00110010 +
1,
b00110010 4
#391
0,
#392
b00000010 %
b00111101 &
b01100101 +
1,
b01100101 4
#393
0,
#394
b00000001 %
b00111100 &
b11001010 +
1,
b11001010 4
#395
0,
#396
b00000000 %
b00111011 &
b10010101 +
1,
b10010101 4
#397
0,
#398
1$
b00010110 %
b00111010 &
b00101010 +
1,
b00101010 4
15
#399
0,
#400
0$
b00010101 %
b00111001 &
b00111111 (
b00000000000000000000000000000110 )
b00000000000000000000000000000111 *
b01010101 +
1,
b00111111 1
b01010101 4
05
#401
0,
#402
b00010100 %
b00111000 &
b10101010 +
1,
b10101010 4
#403
0,
#404
b00010011 %
b00110111 &
b01010100 +
1,
b01010100 4
#405
0,
#406
b00010010 %
b00110110 &
b10101001 +
1,
b10101001 4
#407
0,
#408
b00010001 %
b00110101 &
b01010010 +
1,
b01010010 4
#409
0,
#410
b00010000 %
b00110100 &
b10100100 +
1,
b10100100 4
#411
0,
#412
b00001111 %
b00110011 &
b01001001 +
1,
b01001001 4
#413
0,
#414
b00001110 %
b00110010 &
b10010010 +
1,
b10010010 4
#415
0,
#416
b00001101 %
b00110001 &
b00100100 +
1,
b00100100 4
#417
0,
#418
b00001100 %
b00110000 &
b01001000 +
1,
b01001000 4
#419
0,
#420
b00001011 %
b00101111 &
b10010001 +
1,
b10010001 4
#421
0,
#422
b00001010 %
b00101110 &
b00100010 +
1,
b00100010 4
#423
0,
#424
b00001001 %
b00101101 &
b01000101 +
1,
b01000101 4
#425
0,
#426
b00001000 %
b00101100 &
b10001010 +
1,
b10001010 4
#427
0,
#428
b00000111 %
b00101011 &
b00010100 +
1,
b00010100 4
#429
0,
#430
b00000110 %
b00101010 &
b00101000 +
1,
b00101000 4
#431
0,
#432
b00000101 %
b00101001 &
b01010000 +
1,
b01010000 4
#433
0,
#434
b00000100 %
b00101000 &
b10100001 +
1,
b10100001 4
#435
0,
#436
b00000011 %
b00100111 &
b01000010 +
1,
b01000010 4
#437
0,
#438
b00000010 %
b00100110 &
b10000100 +
1,
b10000100 4
#439
0,
#440
b00000001 %
b00100101 &
b00001001 +
1,
b00001001 4
#441
0,
#442
b00000000 %
b00100100 &
b00010011 +
1,
b00010011 4
#443
0,
#444
1$
b00010110 %
b00100011 &
b00100110 +
1,
b00100110 4
15
#445
0,
#446
0$
b00010101 %
b00100010 &
b01111111 (
b00000000000000000000000000000111 )
b00000000000000000000000000001000 *
b01001101 +
1,
b01111111 1
b01001101 4
05
#447
0,
#448
b00010100 %
b00100001 &
b10011010 +
1,
b10011010 4
#449
0,
#450
b00010011 %
b00100000 &
b00110100 +
1,
b00110100 4
#451
0,
#452
b00010010 %
b00011111 &
b01101000 +
1,
b01101000 4
#453
0,
#454
b00010001 %
b00011110 &
b11010001 +
1,
b11010001 4
#455
0,
#456
b00010000 %
b00011101 &
b10100011 +
1,
b10100011 4
#457
0,
#458
b00001111 %
b00011100 &
b01000111 +
1,
b01000111 4
#459
0,
#460
b00001110 %
b00011011 &
b10001111 +
1,
b10001111 4
#461
0,
#462
b00001101 %
b00011010 &
b00011111 +
1,
b00011111 4
#463
0,
#464
b00001100 %
b00011001 &
b00111110 +
1,
b00111110 4
#465
0,
#466
b00001011 %
b00011000 &
b01111101 +
1,
b01111101 4
#467
0,
#468
b00001010 %
b00010111 &
b11111010 +
1,
b11111010 4
#469
0,
#470
b00001001 %
b00010110 &
b11110101 +
1,
b11110101 4
#471
0,
#472
b00001000 %
b00010101 &
b11101011 +
1,
b11101011 4
#473
0,
#474
b00000111 %
b00010100 &
b11010110 +
1,
b11010110 4
#475
0,
#476
b00000110 %
b00010011 &
b10101101 +
1,
b10101101 4
#477
0,
#478
b00000101 %
b00010010 &
b01011010 +
1,
b01011010 4
#479
0,
#480
b00000100 %
b00010001 &
b10110100 +
1,
b10110100 4
#481
0,
#482
b00000011 %
b00010000 &
b01101001 +
1,
b01101001 4
#483
0,
#484
b00000010 %
b00001111 &
b11010010 +
1,
b11010010 4
#485
0,
#486
b00000001 %
b00001110 &
b10100101 +
1,
b10100101 4
#487
0,
#488
b00000000 %
b00001101 &
b01001010 +
1,
b01001010 4
#489
0,
#490
1$
b00010110 %
b00001100 &
b10010100 +
1,
b10010100 4
15
#491
0,
#492
0$
b00010101 %
b00001011 &
b11111111 (
b00000000000000000000000000001000 )
b00000000000000000000000000000000 *
b00101001 +
1,
b11111111 1
02
13
b00101001 4
05
b00000000000000000000000000000001 6
#493
0,
#494
b00101000 &
b00000000000000000000000000000001 '
b01010011 +
1,
b01010011 4
#495
0,
#496
b01010010 &
b10100111 +
1,
b10100111 4
#497
0,
#498
b10100110 &
b01001111 +
1,
b01001111 4
#499
0,
#500
b01001110 &
b10011111 +
1,
b10011111 4
#501
0,
#502
b10011110 &
b00111111 +
1,
b00111111 4
#503
0,
#504
b00111110 &
b01111110 +
1,
b01111110 4
#505
0,
#506
b01111101 &
b11111100 +
1,
b11111100 4
#507
0,
#508
b11111011 &
b11111000 +
1,
b11111000 4
#509
0,
#510
b11110111 &
b11110000 +
1,
b11110000 4
#511
0,
#512
b11101111 &
b11100000 +
1,
b11100000 4
#513
0,
#514
b11011111 &
b11000000 +
1,
b11000000 4
#515
0,
#516
b10111111 &
b10000000 +
1,
b10000000 4
#517
0,
#518
b01111111 &
b00000001 +
1,
b00000001 4
#519
0,
#520
b00000000 &
b00000011 +
1,
b00000011 4
b00000000000000000000000000000010 6
#521
0,
#522
1#
b00000010 &
b00000000000000000000000000000010 '
b00000110 +
1,
b00000110 4
15
b00000000000000000000000000000011 6
#523
0,
#524
0#
b00000101 &
b00000000000000000000000000000011 '
b00000000 (
b00000000000000000000000000000000 )
b00000000000000000000000000000001 *
b00001101 +
1,
b00000000 1
03
b00001101 4
05
b00000000000000000000000000000000 6
#525
0,
#526
b00000100 &
b00000000000000000000000000000000 '
b00011011 +
1,
b00011011 4
#527
0,
#528
b00000011 &
b00110110 +
1,
b00110110 4
#529
0,
#530
b00000010 &
b01101101 +
1,
b01101101 4
#531
0,
#532
b00000001 &
b11011010 +
1,
b11011010 4
#533
0,
#534
b00000000 &
b10110101 +
1,
b10110101 4
#535
0,
#536
b10110100 &
b01101010 +
1,
b01101010 4
#537
0,
#538
b10110011 &
b11010100 +
1,
b11010100 4
#539
0,
#540
b10110010 &
b10101000 +
1,
b10101000 4
#541
0,
#542
b10110001 &
b01010001 +
1,
b01010001 4
#543
0,
#544
b10110000 &
b10100010 +
1,
b10100010 4
#545
0,
#546
b10101111 &
b01000100 +
1,
b01000100 4
#547
0,
#548
b10101110 &
b10001001 +
1,
10
b10001001 4
#549
0,
#550
b10101101 &
b00000001 (
b00000000000000000000000000000001 )
b00000000000000000000000000000010 *
b00010010 +
1,
00
b00000001 1
12
b00010010 4
#551
0,
#552
b00010100 %
b10101100 &
b00100101 +
1,
b00100101 4
#553
0,
#554
b00010011 %
b10101011 &
b01001011 +
1,
b01001011 4
#555
0,
#556
b00010010 %
b10101010 &
b10010111 +
1,
b10010111 4
#557
0,
#558
b00010001 %
b10101001 &
b00101111 +
1,
b00101111 4
#559
0,
#560
b00010000 %
b10101000 &
b01011110 +
1,
b01011110 4
#561
0,
#562
b00001111 %
b10100111 &
b10111100 +
1,
b10111100 4
#563
0,
#564
b00001110 %
b10100110 &
b01111001 +
1,
b01111001 4
#565
0,
#566
b00001101 %
b10100101 &
b11110010 +
1,
b11110010 4
#567
0,
#568
b00001100 %
b10100100 &
b11100101 +
1,
b11100101 4
#569
0,
#570
b00001011 %
b10100011 &
b11001011 +
1,
b11001011 4
#571
0,
#572
b00001010 %
b10100010 &
b10010110 +
1,
b10010110 4
#573
0,
#574
b00001001 %
b10100001 &
b00101100 +
1,
b00101100 4
#575
0,
#576
b00001000 %
b10100000 &
b01011000 +
1,
b01011000 4
#577
0,
