task3/ram.sv
module ram #(
    parameter   ADDRESS_WIDTH = 9,
                DATA_WIDTH = 8

    )(
        input logic                     clk,
        input logic                     wr,
        input logic                     rd,
        input logic [DATA_WIDTH-1:0]    mic_signal,
        input logic [ADDRESS_WIDTH-1:0] addr0, // read
        input logic [ADDRESS_WIDTH-1:0] addr1, // write
        output logic [DATA_WIDTH-1:0]   dout
    );

    logic [DATA_WIDTH-1:0] rom_array [2**ADDRESS_WIDTH-1:0];
    logic dumb;

    always_ff @(posedge clk)
        begin
            if(wr) rom_array[addr1] <= mic_signal;
            if(rd) dout <= rom_array[addr0];
        end

endmodule

task3/counter.sv

module counter #(
	parameter WIDTH = 8	
)(
	// interface signals
	input logic		clk,
	input logic 	rst,
	input logic		en,
	output logic [WIDTH-1:0] count 
);

always_ff @(posedge clk, posedge rst) 
	if(rst) count <= {WIDTH{1'b0}};

	else if (en) count <= count + {{WIDTH-1{1'b0}}, en};
	else if (!(en)) count <= count - {{WIDTH-1{1'b0}}, en};
	
endmodule

Lab_2_Complete/task3/sigdelay.sv
module sigdelay#(
    parameter A_WIDTH = 9,
              D_WIDTH = 8
)(
    input logic         clk,
    input logic         rst,
    input logic         wr,
    input logic         rd,
    input logic [A_WIDTH-1:0] offset,
    input logic [D_WIDTH-1:0] mic_signal,
    output logic [D_WIDTH-1:0] delayed_signal
);

logic [A_WIDTH-1:0]  readAddress = 9'b0;
logic [A_WIDTH-1:0]  writeAddress = readAddress + offset;


counter wAddrCounter(
    .clk(clk),
    .rst (rst),
    .en (1),
    .count (writeAddress)
);

counter rAddrCounter(
    .clk(clk),
    .rst (rst),
    .en (1),
    .count (readAddress)
);

ram dualPortRam(
    .clk(clk),
    .wr(wr),
    .rd(rd),
    .mic_signal(mic_signal),
    .addr0(readAddress),
    .addr1(writeAddress),
    .dout(delayed_signal)
);

endmodule

task3/sigdelay.vcd
$version Generated by VerilatedVcd $end
$date Thu Nov  3 16:47:55 2022 $end
$timescale 1ps $end

 $scope module TOP $end
  $var wire  1 ' clk $end
  $var wire  8 - delayed_signal [7:0] $end
  $var wire  8 , mic_signal [7:0] $end
  $var wire  9 + offset [8:0] $end
  $var wire  1 * rd $end
  $var wire  1 ( rst $end
  $var wire  1 ) wr $end
  $scope module sigdelay $end
   $var wire 32 . A_WIDTH [31:0] $end
   $var wire 32 / D_WIDTH [31:0] $end
   $var wire  1 ' clk $end
   $var wire  8 - delayed_signal [7:0] $end
   $var wire  8 , mic_signal [7:0] $end
   $var wire  9 + offset [8:0] $end
   $var wire  1 * rd $end
   $var wire  9 # readAddress [8:0] $end
   $var wire  1 ( rst $end
   $var wire  1 ) wr $end
   $var wire  9 $ writeAddress [8:0] $end
   $scope module dualPortRam $end
    $var wire 32 . ADDRESS_WIDTH [31:0] $end
    $var wire 32 / DATA_WIDTH [31:0] $end
    $var wire  9 # addr0 [8:0] $end
    $var wire  9 $ addr1 [8:0] $end
    $var wire  1 ' clk $end
    $var wire  8 - dout [7:0] $end
    $var wire  1 0 dumb $end
    $var wire  8 , mic_signal [7:0] $end
    $var wire  1 * rd $end
    $var wire  1 ) wr $end
   $upscope $end
   $scope module rAddrCounter $end
    $var wire 32 / WIDTH [31:0] $end
    $var wire  1 ' clk $end
    $var wire  8 % count [7:0] $end
    $var wire  1 1 en $end
    $var wire  1 ( rst $end
   $upscope $end
   $scope module wAddrCounter $end
    $var wire 32 / WIDTH [31:0] $end
    $var wire  1 ' clk $end
    $var wire  8 & count [7:0] $end
    $var wire  1 1 en $end
    $var wire  1 ( rst $end
   $upscope $end
  $upscope $end
 $upscope $end
$enddefinitions $end


#0
b000000000 #
b000000000 $
b00000000 %
b00000000 &
1'
0(
1)
1*
b000000000 +
b00000000 ,
b00000000 -
b00000000000000000000000000001001 .
b00000000000000000000000000001000 /
00
11
#1
0'
#2
b000000001 #
b000000001 $
b00000001 %
b00000001 &
1'
b000000110 +
b01101011 ,
#3
0'
#4
b000000010 #
b000000010 $
b00000010 %
b00000010 &
1'
b01101010 ,
#5
0'
#6
b000000011 #
b000000011 $
b00000011 %
b00000011 &
1'
b01100111 ,
#7
0'
#8
b000000100 #
b000000100 $
b00000100 %
b00000100 &
1'
#9
0'
#10
b000000101 #
b000000101 $
b00000101 %
b00000101 &
1'
#11
0'
#12
b000000110 #
b000000110 $
b00000110 %
b00000110 &
1'
b01100100 ,
#13
0'
#14
b000000111 #
b000000111 $
b00000111 %
b00000111 &
1'
#15
0'
#16
b000001000 #
b000001000 $
b00001000 %
b00001000 &
1'
b01100011 ,
#17
0'
#18
b000001001 #
b000001001 $
b00001001 %
b00001001 &
1'
b01100001 ,
#19
0'
#20
b000001010 #
b000001010 $
b00001010 %
b00001010 &
1'
#21
0'
#22
b000001011 #
b000001011 $
b00001011 %
b00001011 &
1'
#23
0'
#24
b000001100 #
b000001100 $
b00001100 %
b00001100 &
1'
b01011111 ,
#25
0'
#26
b000001101 #
b000001101 $
b00001101 %
b00001101 &
1'
b01011101 ,
#27
0'
#28
b000001110 #
b000001110 $
b00001110 %
b00001110 &
1'
b01011100 ,
#29
0'
#30
b000001111 #
b000001111 $
b00001111 %
b00001111 &
1'
b01011110 ,
#31
0'
#32
b000010000 #
b000010000 $
b00010000 %
b00010000 &
1'
b01011101 ,
#33
0'
#34
b000010001 #
b000010001 $
b00010001 %
b00010001 &
1'
b01011011 ,
#35
0'
#36
b000010010 #
b000010010 $
b00010010 %
b00010010 &
1'
#37
0'
#38
b000010011 #
b000010011 $
b00010011 %
b00010011 &
1'
b01011100 ,
#39
0'
#40
b000010100 #
b000010100 $
b00010100 %
b00010100 &
1'
b01011111 ,
#41
0'
#42
b000010101 #
b000010101 $
b00010101 %
b00010101 &
1'
b01011101 ,
#43
0'
#44
b000010110 #
b000010110 $
b00010110 %
b00010110 &
1'
b01100000 ,
#45
0'
#46
b000010111 #
b000010111 $
b00010111 %
b00010111 &
1'
b01100010 ,
#47
0'
#48
b000011000 #
b000011000 $
b00011000 %
b00011000 &
1'
b01100011 ,
#49
0'
#50
b000011001 #
b000011001 $
b00011001 %
b00011001 &
1'
b01100101 ,
#51
0'
#52
b000011010 #
b000011010 $
b00011010 %
b00011010 &
1'
b01011010 ,
#53
0'
#54
b000011011 #
b000011011 $
b00011011 %
b00011011 &
1'
b01011001 ,
#55
0'
#56
b000011100 #
b000011100 $
b00011100 %
b00011100 &
1'
b01010101 ,
#57
0'
#58
b000011101 #
b000011101 $
b00011101 %
b00011101 &
1'
b01011010 ,
#59
0'
#60
b000011110 #
b000011110 $
b00011110 %
b00011110 &
1'
b01011001 ,
#61
0'
#62
b000011111 #
b000011111 $
b00011111 %
b00011111 &
1'
b01100010 ,
#63
0'
#64
b000100000 #
b000100000 $
b00100000 %
b00100000 &
1'
b01100101 ,
#65
0'
#66
b000100001 #
b000100001 $
b00100001 %
b00100001 &
1'
b01011000 ,
#67
0'
#68
b000100010 #
b000100010 $
b00100010 %
b00100010 &
1'
b01100001 ,
#69
0'
#70
b000100011 #
b000100011 $
b00100011 %
b00100011 &
1'
b01100111 ,
#71
0'
#72
b000100100 #
b000100100 $
b00100100 %
b00100100 &
1'
b01100110 ,
#73
0'
#74
b000100101 #
b000100101 $
b00100101 %
b00100101 &
1'
b01100111 ,
#75
0'
#76
b000100110 #
b000100110 $
b00100110 %
b00100110 &
1'
b01101101 ,
#77
0'
#78
b000100111 #
b000100111 $
b00100111 %
b00100111 &
1'
b01111001 ,
#79
0'
#80
b000101000 #
b000101000 $
b00101000 %
b00101000 &
1'
b01110111 ,
#81
0'
#82
b000101001 #
b000101001 $
b00101001 %
b00101001 &
1'
b01110110 ,
#83
0'
#84
b000101010 #
b000101010 $
b00101010 %
b00101010 &
1'
b10001000 ,
#85
0'
#86
b000101011 #
b000101011 $
b00101011 %
b00101011 &
1'
b01101110 ,
#87
0'
#88
b000101100 #
b000101100 $
b00101100 %
b00101100 &
1'
b01111100 ,
#89
0'
#90
b000101101 #
b000101101 $
b00101101 %
b00101101 &
1'
b01101111 ,
#91
0'
#92
b000101110 #
b000101110 $
b00101110 %
b00101110 &
1'
b01111100 ,
#93
0'
#94
b000101111 #
b000101111 $
b00101111 %
b00101111 &
1'
b01110010 ,
#95
0'
#96
b000110000 #
b000110000 $
b00110000 %
b00110000 &
1'
b01110000 ,
#97
0'
#98
b000110001 #
b000110001 $
b00110001 %
b00110001 &
1'
b01110011 ,
#99
0'
#100
b000110010 #
b000110010 $
b00110010 %
b00110010 &
1'
b01110111 ,
#101
0'
#102
b000110011 #
b000110011 $
b00110011 %
b00110011 &
1'
b01100101 ,
#103
0'
#104
b000110100 #
b000110100 $
b00110100 %
b00110100 &
1'
b01101001 ,
#105
0'
#106
b000110101 #
b000110101 $
b00110101 %
b00110101 &
1'
b01011101 ,
#107
0'
#108
b000110110 #
b000110110 $
b00110110 %
b00110110 &
1'
b01100010 ,
#109
0'
#110
b000110111 #
b000110111 $
b00110111 %
b00110111 &
1'
b01011100 ,
#111
0'
#112
b000111000 #
b000111000 $
b00111000 %
b00111000 &
1'
b01011101 ,
#113
0'
#114
b000111001 #
b000111001 $
b00111001 %
b00111001 &
1'
b01100010 ,
#115
0'
#116
b000111010 #
b000111010 $
b00111010 %
b00111010 &
1'
b01101000 ,
#117
0'
#118
b000111011 #
b000111011 $
b00111011 %
b00111011 &
1'
b01101101 ,
#119
0'
#120
b000111100 #
b000111100 $
b00111100 %
b00111100 &
1'
b01100110 ,
#121
0'
#122
b000111101 #
b000111101 $
b00111101 %
b00111101 &
1'
b01101111 ,
#123
0'
#124
b000111110 #
b000111110 $
b00111110 %
b00111110 &
1'
#125
0'
#126
b000111111 #
b000111111 $
b00111111 %
b00111111 &
1'
b01110010 ,
#127
0'
#128
b001000000 #
b001000000 $
b01000000 %
b01000000 &
1'
b01101100 ,
#129
0'
#130
b001000001 #
b001000001 $
b01000001 %
b01000001 &
1'
#131
0'
#132
b001000010 #
b001000010 $
b01000010 %
b01000010 &
1'
b01100100 ,
#133
0'
#134
b001000011 #
b001000011 $
b01000011 %
b01000011 &
1'
b01100000 ,
#135
0'
#136
b001000100 #
b001000100 $
b01000100 %
b01000100 &
1'
b01011111 ,
#137
0'
#138
b001000101 #
b001000101 $
b01000101 %
b01000101 &
1'
b01010110 ,
#139
0'
#140
b001000110 #
b001000110 $
b01000110 %
b01000110 &
1'
b01010100 ,
#141
0'
#142
b001000111 #
b001000111 $
b01000111 %
b01000111 &
1'
b01011001 ,
#143
0'
#144
b001001000 #
b001001000 $
b01001000 %
b01001000 &
1'
b01001101 ,
#145
0'
#146
b001001001 #
b001001001 $
b01001001 %
b01001001 &
1'
b01011110 ,
#147
0'
#148
b001001010 #
b001001010 $
b01001010 %
b01001010 &
1'
b01011000 ,
#149
0'
#150
b001001011 #
b001001011 $
b01001011 %
b01001011 &
1'
b01101101 ,
#151
0'
#152
b001001100 #
b001001100 $
b01001100 %
b01001100 &
1'
b01011100 ,
#153
0'
#154
b001001101 #
b001001101 $
b01001101 %
b01001101 &
1'
b01111000 ,
#155
0'
#156
b001001110 #
b001001110 $
b01001110 %
b01001110 &
1'
b01110110 ,
#157
0'
#158
b001001111 #
b001001111 $
b01001111 %
b01001111 &
1'
b01111011 ,
#159
0'
#160
b001010000 #
b001010000 $
b01010000 %
b01010000 &
1'
b01110110 ,
#161
0'
#162
b001010001 #
b001010001 $
b01010001 %
b01010001 &
1'
b10000110 ,
#163
0'
#164
b001010010 #
b001010010 $
b01010010 %
b01010010 &
1'
b01111111 ,
#165
0'
#166
b001010011 #
b001010011 $
b01010011 %
b01010011 &
1'
b01111011 ,
#167
0'
#168
b001010100 #
b001010100 $
b01010100 %
b01010100 &
1'
b01111010 ,
#169
0'
#170
b001010101 #
b001010101 $
b01010101 %
b01010101 &
1'
b01110110 ,
#171
0'
#172
b001010110 #
b001010110 $
b01010110 %
b01010110 &
1'
b01110001 ,
#173
0'
#174
b001010111 #
b001010111 $
b01010111 %
b01010111 &
1'
b01101011 ,
#175
0'
#176
b001011000 #
b001011000 $
b01011000 %
b01011000 &
1'
b01100100 ,
#177
0'
#178
b001011001 #
b001011001 $
b01011001 %
b01011001 &
1'
b01011100 ,
#179
0'
#180
b001011010 #
b001011010 $
b01011010 %
b01011010 &
1'
#181
0'
#182
b001011011 #
b001011011 $
b01011011 %
b01011011 &
1'
b01011011 ,
#183
0'
#184
b001011100 #
b001011100 $
b01011100 %
b01011100 &
1'
b01010010 ,
#185
0'
#186
b001011101 #
b001011101 $
b01011101 %
b01011101 &
1'
b01100001 ,
#187
0'
#188
b001011110 #
b001011110 $
b01011110 %
b01011110 &
1'
b01010110 ,
#189
0'
#190
b001011111 #
b001011111 $
b01011111 %
b01011111 &
1'
b01010100 ,
#191
0'
#192
b001100000 #
b001100000 $
b01100000 %
b01100000 &
1'
#193
0'
#194
b001100001 #
b001100001 $
b01100001 %
b01100001 &
1'
b01010011 ,
#195
0'
#196
b001100010 #
b001100010 $
b01100010 %
b01100010 &
1'
b01010110 ,
#197
0'
#198
b001100011 #
b001100011 $
b01100011 %
b01100011 &
1'
b01010001 ,
#199
0'
#200
b001100100 #
b001100100 $
b01100100 %
b01100100 &
1'
b01010111 ,
#201
0'
#202
b001100101 #
b001100101 $
b01100101 %
b01100101 &
1'
b01010011 ,
#203
0'
#204
b001100110 #
b001100110 $
b01100110 %
b01100110 &
1'
b01011100 ,
#205
0'
#206
b001100111 #
b001100111 $
b01100111 %
b01100111 &
1'
b01010100 ,
#207
0'
#208
b001101000 #
b001101000 $
b01101000 %
b01101000 &
1'
b01011101 ,
#209
0'
#210
b001101001 #
b001101001 $
b01101001 %
b01101001 &
1'
b01011110 ,
#211
0'
#212
b001101010 #
b001101010 $
b01101010 %
b01101010 &
1'
b01100100 ,
#213
0'
#214
b001101011 #
b001101011 $
b01101011 %
b01101011 &
1'
b01011110 ,
#215
0'
#216
b001101100 #
b001101100 $
b01101100 %
b01101100 &
1'
b01100001 ,
#217
0'
#218
b001101101 #
b001101101 $
b01101101 %
b01101101 &
1'
b01100010 ,
#219
0'
#220
b001101110 #
b001101110 $
b01101110 %
b01101110 &
1'
b01100000 ,
#221
0'
#222
b001101111 #
b001101111 $
b01101111 %
b01101111 &
1'
b01101001 ,
#223
0'
#224
b001110000 #
b001110000 $
b01110000 %
b01110000 &
1'
b01011010 ,
#225
0'
#226
b001110001 #
b001110001 $
b01110001 %
b01110001 &
1'
b01100110 ,
#227
0'
#228
b001110010 #
b001110010 $
b01110010 %
b01110010 &
1'
b01101000 ,
#229
0'
#230
b001110011 #
b001110011 $
b01110011 %
b01110011 &
1'
#231
0'
#232
b001110100 #
b001110100 $
b01110100 %
b01110100 &
1'
b01101111 ,
#233
0'
#234
b001110101 #
b001110101 $
b01110101 %
b01110101 &
1'
b01101000 ,
#235
0'
#236
b001110110 #
b001110110 $
b01110110 %
b01110110 &
1'
b01111110 ,
#237
0'
#238
b001110111 #
b001110111 $
b01110111 %
b01110111 &
1'
b01111000 ,
#239
0'
#240
b001111000 #
b001111000 $
b01111000 %
b01111000 &
1'
b01110100 ,
#241
0'
#242
b001111001 #
b001111001 $
b01111001 %
b01111001 &
1'
b01111111 ,
#243
0'
#244
b001111010 #
b001111010 $
b01111010 %
b01111010 &
1'
b01111010 ,
#245
0'
#246
b001111011 #
b001111011 $
b01111011 %
b01111011 &
1'
b01110001 ,
#247
0'
#248
b001111100 #
b001111100 $
b01111100 %
b01111100 &
1'
b01101010 ,
#249
0'
#250
b001111101 #
b001111101 $
b01111101 %
b01111101 &
1'
b01100001 ,
#251
0'
#252
b001111110 #
b001111110 $
b01111110 %
b01111110 &
1'
b01100111 ,
#253
0'
#254
b001111111 #
b001111111 $
b01111111 %
b01111111 &
1'
b01100011 ,
#255
0'
#256
b010000000 #
b010000000 $
b10000000 %
b10000000 &
1'
b01001001 ,
#257
0'
#258
b010000001 #
b010000001 $
b10000001 %
b10000001 &
1'
b01010110 ,
#259
0'
#260
b010000010 #
b010000010 $
b10000010 %
b10000010 &
1'
b01001100 ,
#261
0'
#262
b010000011 #
b010000011 $
b10000011 %
b10000011 &
1'
b01010010 ,
#263
0'
#264
b010000100 #
b010000100 $
b10000100 %
b10000100 &
1'
b01000111 ,
#265
0'
#266
b010000101 #
b010000101 $
b10000101 %
b10000101 &
1'
b01001111 ,
#267
0'
#268
b010000110 #
b010000110 $
b10000110 %
b10000110 &
1'
b01100100 ,
#269
0'
#270
b010000111 #
b010000111 $
b10000111 %
b10000111 &
1'
b01011101 ,
#271
0'
#272
b010001000 #
b010001000 $
b10001000 %
b10001000 &
1'
b01100101 ,
#273
0'
#274
b010001001 #
b010001001 $
b10001001 %
b10001001 &
1'
b01101101 ,
#275
0'
#276
b010001010 #
b010001010 $
b10001010 %
b10001010 &
1'
b01110100 ,
#277
0'
#278
b010001011 #
b010001011 $
b10001011 %
b10001011 &
1'
b01101011 ,
#279
0'
#280
b010001100 #
b010001100 $
b10001100 %
b10001100 &
1'
b01011111 ,
#281
0'
#282
b010001101 #
b010001101 $
b10001101 %
b10001101 &
1'
b01101111 ,
#283
0'
#284
b010001110 #
b010001110 $
b10001110 %
b10001110 &
1'
b01011001 ,
#285
0'
#286
b010001111 #
b010001111 $
b10001111 %
b10001111 &
1'
b01011100 ,
#287
0'
#288
b010010000 #
b010010000 $
b10010000 %
b10010000 &
1'
b01010101 ,
#289
0'
#290
b010010001 #
b010010001 $
b10010001 %
b10010001 &
1'
b01010110 ,
#291
0'
#292
b010010010 #
b010010010 $
b10010010 %
b10010010 &
1'
b01011110 ,
#293
0'
#294
b010010011 #
b010010011 $
b10010011 %
b10010011 &
1'
b01011101 ,
#295
0'
#296
b010010100 #
b010010100 $
b10010100 %
b10010100 &
1'
b01010101 ,
#297
0'
#298
b010010101 #
b010010101 $
b10010101 %
b10010101 &
1'
b01011110 ,
#299
0'
#300
b010010110 #
b010010110 $
b10010110 %
b10010110 &
1'
#301
0'
#302
b010010111 #
b010010111 $
b10010111 %
b10010111 &
1'
b01100001 ,
#303
0'
#304
b010011000 #
b010011000 $
b10011000 %
b10011000 &
1'
b01100000 ,
#305
0'
#306
b010011001 #
b010011001 $
b10011001 %
b10011001 &
1'
b01110111 ,
#307
0'
#308
b010011010 #
b010011010 $
b10011010 %
b10011010 &
1'
b01110110 ,
#309
0'
#310
b010011011 #
b010011011 $
b10011011 %
b10011011 &
1'
b10000001 ,
#311
0'
#312
b010011100 #
b010011100 $
b10011100 %
b10011100 &
1'
b01111111 ,
#313
0'
#314
b010011101 #
b010011101 $
b10011101 %
b10011101 &
1'
b10010000 ,
#315
0'
#316
b010011110 #
b010011110 $
b10011110 %
b10011110 &
1'
b10000010 ,
#317
0'
#318
b010011111 #
b010011111 $
b10011111 %
b10011111 &
1'
b01111110 ,
#319
0'
#320
b010100000 #
b010100000 $
b10100000 %
b10100000 &
1'
b01110110 ,
#321
0'
#322
b010100001 #
b010100001 $
b10100001 %
b10100001 &
1'
b01110101 ,
#323
0'
#324
b010100010 #
b010100010 $
b10100010 %
b10100010 &
1'
b01101111 ,
#325
0'
#326
b010100011 #
b010100011 $
b10100011 %
b10100011 &
1'
b01100011 ,
#327
0'
#328
b010100100 #
b010100100 $
b10100100 %
b10100100 &
1'
b01011001 ,
#329
0'
#330
b010100101 #
b010100101 $
b10100101 %
b10100101 &
1'
b01011010 ,
#331
0'
#332
b010100110 #
b010100110 $
b10100110 %
b10100110 &
1'
b01001110 ,
#333
0'
#334
b010100111 #
b010100111 $
b10100111 %
b10100111 &
1'
b01001001 ,
#335
0'
#336
b010101000 #
b010101000 $
b10101000 %
b10101000 &
1'
b01001101 ,
#337
0'
#338
b010101001 #
b010101001 $
b10101001 %
b10101001 &
1'
b01000101 ,
#339
0'
#340
b010101010 #
b010101010 $
b10101010 %
b10101010 &
1'
b00111010 ,
#341
0'
#342
b010101011 #
b010101011 $
b10101011 %
b10101011 &
1'
b00111011 ,
#343
0'
#344
b010101100 #
b010101100 $
b10101100 %
b10101100 &
1'
#345
0'
#346
b010101101 #
b010101101 $
b10101101 %
b10101101 &
1'
b01001001 ,
#347
0'
#348
b010101110 #
b010101110 $
b10101110 %
b10101110 &
1'
b01010011 ,
#349
0'
#350
b010101111 #
b010101111 $
b10101111 %
b10101111 &
1'
b01011011 ,
#351
0'
#352
b010110000 #
b010110000 $
b10110000 %
b10110000 &
1'
b01101010 ,
#353
0'
#354
b010110001 #
b010110001 $
b10110001 %
b10110001 &
1'
b01111001 ,
#355
0'
#356
b010110010 #
b010110010 $
b10110010 %
b10110010 &
1'
b01111101 ,
#357
0'
#358
b010110011 #
b010110011 $
b10110011 %
b10110011 &
1'
#359
0'
#360
b010110100 #
b010110100 $
b10110100 %
b10110100 &
1'
b01110110 ,
#361
0'
#362
b010110101 #
b010110101 $
b10110101 %
b10110101 &
1'
b01110001 ,
#363
0'
#364
b010110110 #
b010110110 $
b10110110 %
b10110110 &
1'
#365
0'
#366
b010110111 #
b010110111 $
b10110111 %
b10110111 &
1'
b01100011 ,
#367
0'
#368
b010111000 #
b010111000 $
b10111000 %
b10111000 &
1'
b01101001 ,
#369
0'
#370
b010111001 #
b010111001 $
b10111001 %
b10111001 &
1'
b01100101 ,
#371
0'
#372
b010111010 #
b010111010 $
b10111010 %
b10111010 &
1'
b01010011 ,
#373
0'
#374
b010111011 #
b010111011 $
b10111011 %
b10111011 &
1'
b01101001 ,
#375
0'
#376
b010111100 #
b010111100 $
b10111100 %
b10111100 &
1'
b01011101 ,
#377
0'
#378
b010111101 #
b010111101 $
b10111101 %
b10111101 &
1'
b01100000 ,
#379
0'
#380
b010111110 #
b010111110 $
b10111110 %
b10111110 &
1'
b01110110 ,
#381
0'
#382
b010111111 #
b010111111 $
b10111111 %
b10111111 &
1'
b01111100 ,
#383
0'
#384
b011000000 #
b011000000 $
b11000000 %
b11000000 &
1'
b01110001 ,
#385
0'
#386
b011000001 #
b011000001 $
b11000001 %
b11000001 &
1'
b10000100 ,
#387
0'
#388
b011000010 #
b011000010 $
b11000010 %
b11000010 &
1'
b10000101 ,
#389
0'
#390
b011000011 #
b011000011 $
b11000011 %
b11000011 &
1'
b01110101 ,
#391
0'
#392
b011000100 #
b011000100 $
b11000100 %
b11000100 &
1'
b10000011 ,
#393
0'
#394
b011000101 #
b011000101 $
b11000101 %
b11000101 &
1'
b01101001 ,
#395
0'
#396
b011000110 #
b011000110 $
b11000110 %
b11000110 &
1'
#397
0'
#398
b011000111 #
b011000111 $
b11000111 %
b11000111 &
1'
b01100001 ,
#399
0'
#400
b011001000 #
b011001000 $
b11001000 %
b11001000 &
1'
b01010000 ,
#401
0'
#402
b011001001 #
b011001001 $
b11001001 %
b11001001 &
1'
b01010011 ,
#403
0'
#404
b011001010 #
b011001010 $
b11001010 %
b11001010 &
1'
b01000110 ,
#405
0'
#406
b011001011 #
b011001011 $
b11001011 %
b11001011 &
1'
b01001011 ,
#407
0'
#408
b011001100 #
b011001100 $
b11001100 %
b11001100 &
1'
b01001110 ,
#409
0'
#410
b011001101 #
b011001101 $
b11001101 %
b11001101 &
1'
b01010001 ,
#411
0'
#412
b011001110 #
b011001110 $
b11001110 %
b11001110 &
1'
b01010100 ,
#413
0'
#414
b011001111 #
b011001111 $
b11001111 %
b11001111 &
1'
b01001110 ,
#415
0'
#416
b011010000 #
b011010000 $
b11010000 %
b11010000 &
1'
b01011000 ,
#417
0'
#418
b011010001 #
b011010001 $
b11010001 %
b11010001 &
1'
b01011011 ,
#419
0'
#420
b011010010 #
b011010010 $
b11010010 %
b11010010 &
1'
b01100001 ,
#421
0'
#422
b011010011 #
b011010011 $
b11010011 %
b11010011 &
1'
b01100000 ,
#423
0'
#424
b011010100 #
b011010100 $
b11010100 %
b11010100 &
1'
b01110110 ,
#425
0'
#426
b011010101 #
b011010101 $
b11010101 %
b11010101 &
1'
b01100100 ,
#427
0'
#428
b011010110 #
b011010110 $
b11010110 %
b11010110 &
1'
b01110101 ,
#429
0'
#430
b011010111 #
b011010111 $
b11010111 %
b11010111 &
1'
b01110010 ,
#431
0'
#432
b011011000 #
b011011000 $
b11011000 %
b11011000 &
1'
b01110101 ,
#433
0'
#434
b011011001 #
b011011001 $
b11011001 %
b11011001 &
1'
b01110000 ,
#435
0'
#436
b011011010 #
b011011010 $
b11011010 %
b11011010 &
1'
b01100110 ,
#437
0'
#438
b011011011 #
b011011011 $
b11011011 %
b11011011 &
1'
b01110100 ,
#439
0'
#440
b011011100 #
b011011100 $
b11011100 %
b11011100 &
1'
b01100000 ,
#441
0'
#442
b011011101 #
b011011101 $
b11011101 %
b11011101 &
1'
b01101111 ,
#443
0'
#444
b011011110 #
b011011110 $
b11011110 %
b11011110 &
1'
b01011011 ,
#445
0'
#446
b011011111 #
b011011111 $
b11011111 %
b11011111 &
1'
b01101010 ,
#447
0'
#448
b011100000 #
b011100000 $
b11100000 %
b11100000 &
1'
b01100010 ,
#449
0'
#450
b011100001 #
b011100001 $
b11100001 %
b11100001 &
1'
b01100000 ,
#451
0'
#452
b011100010 #
b011100010 $
b11100010 %
b11100010 &
1'
b01100100 ,
#453
0'
#454
b011100011 #
b011100011 $
b11100011 %
b11100011 &
1'
b01011101 ,
#455
0'
#456
b011100100 #
b011100100 $
b11100100 %
b11100100 &
1'
b01100001 ,
#457
0'
#458
b011100101 #
b011100101 $
b11100101 %
b11100101 &
1'
b01011110 ,
#459
0'
#460
b011100110 #
b011100110 $
b11100110 %
b11100110 &
1'
b01100111 ,
#461
0'
#462
b011100111 #
b011100111 $
b11100111 %
b11100111 &
1'
b01101000 ,
#463
0'
#464
b011101000 #
b011101000 $
b11101000 %
b11101000 &
1'
b01111101 ,
#465
0'
#466
b011101001 #
b011101001 $
b11101001 %
b11101001 &
1'
b01101110 ,
#467
0'
#468
b011101010 #
b011101010 $
b11101010 %
b11101010 &
1'
b10001101 ,
#469
0'
#470
b011101011 #
b011101011 $
b11101011 %
b11101011 &
1'
b10000111 ,
#471
0'
#472
b011101100 #
b011101100 $
b11101100 %
b11101100 &
1'
#473
0'
#474
b011101101 #
b011101101 $
b11101101 %
b11101101 &
1'
#475
0'
#476
b011101110 #
b011101110 $
b11101110 %
b11101110 &
1'
b10000000 ,
#477
0'
#478
b011101111 #
b011101111 $
b11101111 %
b11101111 &
1'
b01101101 ,
#479
0'
#480
b011110000 #
b011110000 $
b11110000 %
b11110000 &
1'
b01101001 ,
#481
0'
#482
b011110001 #
b011110001 $
b11110001 %
b11110001 &
1'
b01101100 ,
#483
0'
#484
b011110010 #
b011110010 $
b11110010 %
b11110010 &
1'
b01011100 ,
#485
0'
#486
b011110011 #
b011110011 $
b11110011 %
b11110011 &
1'
#487
0'
#488
b011110100 #
b011110100 $
b11110100 %
b11110100 &
1'
b01010011 ,
#489
0'
#490
b011110101 #
b011110101 $
b11110101 %
b11110101 &
1'
b01001111 ,
#491
0'
#492
b011110110 #
b011110110 $
b11110110 %
b11110110 &
1'
b01010000 ,
#493
0'
#494
b011110111 #
b011110111 $
b11110111 %
b11110111 &
1'
b01001110 ,
#495
0'
#496
b011111000 #
b011111000 $
b11111000 %
b11111000 &
1'
b01000100 ,
#497
0'
#498
b011111001 #
b011111001 $
b11111001 %
b11111001 &
1'
b01010111 ,
#499
0'
#500
b011111010 #
b011111010 $
b11111010 %
b11111010 &
1'
b01001111 ,
#501
0'
#502
b011111011 #
b011111011 $
b11111011 %
b11111011 &
1'
b01011101 ,
#503
0'
#504
b011111100 #
b011111100 $
b11111100 %
b11111100 &
1'
b01100111 ,
#505
0'
#506
b011111101 #
b011111101 $
b11111101 %
b11111101 &
1'
b01101001 ,
#507
0'
#508
b011111110 #
b011111110 $
b11111110 %
b11111110 &
1'
b01111100 ,
#509
0'
#510
b011111111 #
b011111111 $
b11111111 %
b11111111 &
1'
b10000001 ,
#511
0'
#512
b000000000 #
b000000000 $
b00000000 %
b00000000 &
1'
b01110001 ,
#513
0'
#514
b000000001 #
b000000001 $
b00000001 %
b00000001 &
1'
#515
0'
#516
b000000010 #
b000000010 $
b00000010 %
b00000010 &
1'
b01100001 ,
b01101011 -
#517
0'
#518
b000000011 #
b000000011 $
b00000011 %
b00000011 &
1'
b01011010 ,
b01101010 -
#519
0'
#520
b000000100 #
b000000100 $
b00000100 %
b00000100 &
1'
b01010100 ,
b01100111 -
#521
0'
#522
b000000101 #
b000000101 $
b00000101 %
b00000101 &
1'
b01000110 ,
#523
0'
#524
b000000110 #
b000000110 $
b00000110 %
b00000110 &
1'
b01011011 ,
#525
0'
#526
b000000111 #
b000000111 $
b00000111 %
b00000111 &
1'
b01010100 ,
b01100100 -
#527
0'
#528
b000001000 #
b000001000 $
b00001000 %
b00001000 &
1'
b01011001 ,
#529
0'
#530
b000001001 #
b000001001 $
b00001001 %
b00001001 &
1'
b01100010 ,
b01100011 -
#531
0'
#532
b000001010 #
b000001010 $
b00001010 %
b00001010 &
1'
b01101101 ,
b01100001 -
#533
0'
#534
b000001011 #
b000001011 $
b00001011 %
b00001011 &
1'
b01101001 ,
#535
0'
#536
b000001100 #
b000001100 $
b00001100 %
b00001100 &
1'
b01110101 ,
#537
0'
#538
b000001101 #
b000001101 $
b00001101 %
b00001101 &
1'
b01110111 ,
b01011111 -
#539
0'
#540
b000001110 #
b000001110 $
b00001110 %
b00001110 &
1'
b01111111 ,
b01011101 -
#541
0'
#542
b000001111 #
b000001111 $
b00001111 %
b00001111 &
1'
b01101111 ,
b01011100 -
#543
0'
#544
b000010000 #
b000010000 $
b00010000 %
b00010000 &
1'
b10000101 ,
b01011110 -
#545
0'
#546
b000010001 #
b000010001 $
b00010001 %
b00010001 &
1'
b01111000 ,
b01011101 -
#547
0'
