task4_with_timer/f1fsm.sv
module f1fsm(
    input logic clk,
    input logic en, 
    input logic rst,
    input logic trigger,
    output logic [7:0] dout,
    output logic cmd_delay,
    output logic cmd_seq
);

    logic [7:0] num = 8'b0;
    
    typedef enum {IDLE, S0, S1, S2, S3, S4, S5, S6, S7} light_state;
    light_state current_state, next_state;


    always_ff @(posedge clk) begin
        if (rst) current_state <= IDLE;
        
        if (current_state == IDLE) begin
            if (trigger) current_state <= next_state;
        end
        
        else begin
            if (en) current_state <= next_state;
            else current_state <= current_state;
        end

    end

    always_comb begin
        case (current_state)
        IDLE:   next_state = S0;
        S0:     next_state = S1;
        S1:     next_state = S2;
        S2:     next_state = S3;     
        S3:     next_state = S4;
        S4:     next_state = S5;
        S5:     next_state = S6;
        S6:     next_state = S7;
        S7:     next_state = IDLE;        
        endcase    
    end

    always_comb begin
        case(current_state)
                IDLE:   begin 
                        num = 8'b0;
                        cmd_delay = 1'b0;
                        cmd_seq = 1'b0;
                end
                
                S0:     begin 
                        num = 8'b1;
                        cmd_seq = 1'b1;
                end
                S1:     num = 8'b11;     
                S2:     num = 8'b111;     
                S3:     num = 8'b1111;
                S4:     num = 8'b11111;
                S5:     num = 8'b111111;
                S6:     num = 8'b1111111;
                S7:     begin
                        num = 8'b11111111;
                        cmd_delay = 1'b1;
                        cmd_seq = 1'b0;
                end
        endcase
    end

    assign dout = num;

endmodule

task4/delay.sv
module delay #(
	parameter WIDTH = 10    // no of bits in delay counter
)(
    input   logic               clk,        // clock signal
    input   logic               rst,        // reset signal
    input   logic               trigger,    // trigger input signal
    input   logic [WIDTH-1:0]   n,          // no of clock cycle delay
    output  logic               time_out    // output pulse signal
);
    // Declare counter
    logic [WIDTH-1:0]   count = {WIDTH{1'b0}};            // internal counter

    // Define our states
    typedef enum {IDLE, COUNTING, TIME_OUT, WAIT_LOW}  my_state;
    my_state current_state, next_state;

    // counter
    always_ff @(posedge clk)
        if (rst | trigger | count == {WIDTH{1'b0}}) count <= n - 1'b1;
        else                                count <= count - 1'b1;

    // state transition
    always_ff @(posedge clk)
        if (rst)    current_state <= IDLE;
        else        current_state <= next_state; 

    // next state logic
    always_comb
        case (current_state)
            IDLE:       if (trigger==1'b1)  next_state = COUNTING;
                        else    next_state = current_state;
            
            COUNTING:   if (count=={WIDTH{1'b0}}) next_state = TIME_OUT;
                        else    next_state = current_state;
            
            TIME_OUT:   if (trigger==1'b1)  next_state = WAIT_LOW;
                        else    next_state = IDLE;
            
            WAIT_LOW:   if (trigger==1'b0)  next_state = IDLE;
                        else    next_state = current_state;
            
            default: next_state = IDLE;
        endcase
    
    // output logic
    always_comb
        case (current_state)
            IDLE:       time_out = 1'b0;
            COUNTING:   time_out = 1'b0;
            TIME_OUT:   time_out = 1'b1;
            WAIT_LOW:   time_out = 1'b0;
            default:    time_out = 1'b0;
        endcase
endmodule

task4/lfsr.sv
module lfsr(
    input logic rst,
    input logic en,
    input logic clk,
    output logic [6:0] dout 
);

    logic [6:0] sreg = 7'b1;
    
    assign dout = sreg;

    always_ff @(posedge clk) begin
        if (rst)
            sreg <= 4'b1;
        
        else if(en)
            sreg <= {sreg[5:0], sreg[6] ^ sreg[2]};
    
    end

endmodule

task4_with_timer/clktick.sv
module clktick #(
	parameter WIDTH = 8
)(
  // interface signals
  input  logic             clk,      // clock 
  input  logic             rst,      // reset
  input  logic             en,       // enable signal
  input  logic [WIDTH-1:0] N,     	 // clock divided by N+1
  output logic  		       tick      // tick output
);

logic [WIDTH-1:0] count;

always_ff @ (posedge clk)
    if (rst) begin
        tick <= 1'b0;
        count <= N;  
        end
    else if (en) begin
	    if (count == 0) begin
		    tick <= 1'b1;
		    count <= N;
	        end
	    else begin
		    tick <= 1'b0;
		    count <= count - 1'b1;
	        end
        end
endmodule

task4/top.sv
module top #(
    parameter WIDTH = 16
) (
    input logic clk,
    input logic en, 
    input logic rst,
    input logic [WIDTH-1:0] N,
    input logic trigger,
    output logic [7:0] dout,
    output logic cmd_seq,
    output logic cmd_delay,
    output logic [WIDTH-1:0] n
);

logic delay;
logic mtick;
logic muxout;
// logic [WIDTH-1:0] n;
assign muxout = cmd_seq ? mtick : delay;


clktick clktickr(
    .clk(clk),
    .en(cmd_seq),
    .N(N),
    .rst(rst),
    .tick(mtick)//output
);

lfsr randomdelayer(
    .clk(clk),
    .en(1),
    .rst(rst),
    .dout(n) //output
);

delay delayer(
    .n(n),
    .clk(clk),
    .rst(rst),
    .trigger(cmd_delay),
    .time_out(delay) //output
);

f1fsm f1fsm(
    .en(muxout),
    .clk(clk),
    .rst(rst),
    .trigger(trigger),
    .dout(dout),
    .cmd_delay(cmd_delay),
    .cmd_seq(cmd_seq)
);

  
endmodule

task4/top.vcd
$version Generated by VerilatedVcd $end
$date Sat Nov 12 18:22:52 2022 $end
$timescale 1ps $end

 $scope module TOP $end
  $var wire 16 / N [15:0] $end
  $var wire  1 , clk $end
  $var wire  1 3 cmd_delay $end
  $var wire  1 2 cmd_seq $end
  $var wire  8 1 dout [7:0] $end
  $var wire  1 - en $end
  $var wire 16 4 n [15:0] $end
  $var wire  1 . rst $end
  $var wire  1 0 trigger $end
  $scope module top $end
   $var wire 16 / N [15:0] $end
   $var wire 32 8 WIDTH [31:0] $end
   $var wire  1 , clk $end
   $var wire  1 3 cmd_delay $end
   $var wire  1 2 cmd_seq $end
   $var wire  1 # delay $end
   $var wire  8 1 dout [7:0] $end
   $var wire  1 - en $end
   $var wire  1 $ mtick $end
   $var wire  1 5 muxout $end
   $var wire 16 4 n [15:0] $end
   $var wire  1 . rst $end
   $var wire  1 0 trigger $end
   $scope module clktickr $end
    $var wire 16 / N [15:0] $end
    $var wire 32 8 WIDTH [31:0] $end
    $var wire  1 , clk $end
    $var wire 16 % count [15:0] $end
    $var wire  1 2 en $end
    $var wire  1 . rst $end
    $var wire  1 $ tick $end
   $upscope $end
   $scope module delayer $end
    $var wire 32 9 WIDTH [31:0] $end
    $var wire  1 , clk $end
    $var wire 10 & count [9:0] $end
    $var wire 32 ' current_state [31:0] $end
    $var wire 10 6 n [9:0] $end
    $var wire 32 7 next_state [31:0] $end
    $var wire  1 . rst $end
    $var wire  1 # time_out $end
    $var wire  1 3 trigger $end
   $upscope $end
   $scope module f1fsm $end
    $var wire  1 , clk $end
    $var wire  1 3 cmd_delay $end
    $var wire  1 2 cmd_seq $end
    $var wire 32 ) current_state [31:0] $end
    $var wire  8 1 dout [7:0] $end
    $var wire  1 5 en $end
    $var wire 32 * next_state [31:0] $end
    $var wire  8 ( num [7:0] $end
    $var wire  1 . rst $end
    $var wire  1 0 trigger $end
   $upscope $end
   $scope module randomdelayer $end
    $var wire  1 , clk $end
    $var wire  7 + dout [6:0] $end
    $var wire  1 : en $end
    $var wire  1 . rst $end
    $var wire  7 + sreg [6:0] $end
   $upscope $end
  $upscope $end
 $upscope $end
$enddefinitions $end


#0
0#
0$
b0000000000000000 %
b0000000000 &
b00000000000000000000000000000000 '
b00000000 (
b00000000000000000000000000000000 )
b00000000000000000000000000000000 *
b0000000 +
1,
1-
0.
b0000000000011000 /
00
b00000000 1
02
03
b0000000000000000 4
05
b0000000000 6
b00000000000000000000000000000000 7
b00000000000000000000000000010000 8
b00000000000000000000000000001010 9
1:
#1
b00000000000000000000000000000001 *
b0000001 +
0,
b0000000000000001 4
b0000000001 6
#2
b0000010 +
1,
1.
b0000000000000010 4
b0000000010 6
#3
0,
#4
b0000000000011000 %
b0000000001 &
b0000001 +
1,
b0000000000000001 4
b0000000001 6
#5
0,
#6
b0000000000 &
1,
0.
#7
0,
#8
b0000010 +
1,
b0000000000000010 4
b0000000010 6
#9
0,
#10
b0000000001 &
b0000100 +
1,
b0000000000000100 4
b0000000100 6
#11
0,
#12
b0000000000 &
b0001001 +
1,
b0000000000001001 4
b0000001001 6
#13
0,
#14
b0000001000 &
b0010010 +
1,
b0000000000010010 4
b0000010010 6
#15
0,
#16
b0000000111 &
b0100100 +
1,
b0000000000100100 4
b0000100100 6
#17
0,
#18
b0000000110 &
b1001001 +
1,
b0000000001001001 4
b0001001001 6
#19
0,
#20
b0000000101 &
b0010011 +
1,
b0000000000010011 4
b0000010011 6
#21
0,
#22
b0000000100 &
b0100110 +
1,
b0000000000100110 4
b0000100110 6
#23
0,
#24
b0000000011 &
b1001101 +
1,
b0000000001001101 4
b0001001101 6
#25
0,
#26
b0000000010 &
b0011010 +
1,
b0000000000011010 4
b0000011010 6
#27
0,
#28
b0000000001 &
b0110100 +
1,
b0000000000110100 4
b0000110100 6
#29
0,
#30
b0000000000 &
b1101001 +
1,
b0000000001101001 4
b0001101001 6
#31
0,
#32
b0001101000 &
b1010011 +
1,
b0000000001010011 4
b0001010011 6
#33
0,
#34
b0001100111 &
b0100111 +
1,
b0000000000100111 4
b0000100111 6
#35
0,
#36
b0001100110 &
b1001111 +
1,
b0000000001001111 4
b0001001111 6
#37
0,
#38
b0001100101 &
b0011110 +
1,
b0000000000011110 4
b0000011110 6
#39
0,
#40
b0001100100 &
b0111101 +
1,
b0000000000111101 4
b0000111101 6
#41
0,
#42
b0001100011 &
b1111011 +
1,
b0000000001111011 4
b0001111011 6
#43
0,
#44
b0001100010 &
b1110111 +
1,
b0000000001110111 4
b0001110111 6
#45
0,
#46
b0001100001 &
b1101110 +
1,
b0000000001101110 4
b0001101110 6
#47
0,
#48
b0001100000 &
b1011100 +
1,
b0000000001011100 4
b0001011100 6
#49
0,
#50
b0001011111 &
b0111000 +
1,
b0000000000111000 4
b0000111000 6
#51
0,
#52
b0001011110 &
b1110000 +
1,
b0000000001110000 4
b0001110000 6
#53
0,
#54
b0001011101 &
b1100001 +
1,
b0000000001100001 4
b0001100001 6
#55
0,
#56
b0001011100 &
b1000011 +
1,
b0000000001000011 4
b0001000011 6
#57
0,
#58
b0001011011 &
b0000111 +
1,
b0000000000000111 4
b0000000111 6
#59
0,
#60
b0001011010 &
b0001111 +
1,
b0000000000001111 4
b0000001111 6
#61
0,
#62
b0001011001 &
b0011111 +
1,
b0000000000011111 4
b0000011111 6
#63
0,
#64
b0001011000 &
b0111111 +
1,
b0000000000111111 4
b0000111111 6
#65
0,
#66
b0001010111 &
b1111111 +
1,
b0000000001111111 4
b0001111111 6
#67
0,
#68
b0001010110 &
b1111110 +
1,
b0000000001111110 4
b0001111110 6
#69
0,
#70
b0001010101 &
b1111100 +
1,
b0000000001111100 4
b0001111100 6
#71
0,
#72
b0001010100 &
b1111000 +
1,
b0000000001111000 4
b0001111000 6
#73
0,
#74
b0001010011 &
b1110001 +
1,
b0000000001110001 4
b0001110001 6
#75
0,
#76
b0001010010 &
b1100011 +
1,
b0000000001100011 4
b0001100011 6
#77
0,
#78
b0001010001 &
b1000111 +
1,
b0000000001000111 4
b0001000111 6
#79
0,
#80
b0001010000 &
b0001110 +
1,
b0000000000001110 4
b0000001110 6
#81
0,
#82
b0001001111 &
b0011101 +
1,
b0000000000011101 4
b0000011101 6
#83
0,
#84
b0001001110 &
b0111011 +
1,
b0000000000111011 4
b0000111011 6
#85
0,
#86
b0001001101 &
b1110110 +
1,
b0000000001110110 4
b0001110110 6
#87
0,
#88
b0001001100 &
b1101100 +
1,
b0000000001101100 4
b0001101100 6
#89
0,
#90
b0001001011 &
b1011000 +
1,
b0000000001011000 4
b0001011000 6
#91
0,
#92
b0001001010 &
b0110001 +
1,
b0000000000110001 4
b0000110001 6
#93
0,
#94
b0001001001 &
b1100010 +
1,
b0000000001100010 4
b0001100010 6
#95
0,
#96
b0001001000 &
b1000101 +
1,
b0000000001000101 4
b0001000101 6
#97
0,
#98
b0001000111 &
b0001010 +
1,
b0000000000001010 4
b0000001010 6
#99
0,
#100
b0001000110 &
b0010100 +
1,
b0000000000010100 4
b0000010100 6
#101
0,
#102
b0001000101 &
b0101001 +
1,
b0000000000101001 4
b0000101001 6
#103
0,
#104
b0001000100 &
b1010010 +
1,
b0000000001010010 4
b0001010010 6
#105
0,
#106
b0001000011 &
b0100101 +
1,
b0000000000100101 4
b0000100101 6
#107
0,
#108
b0001000010 &
b1001011 +
1,
b0000000001001011 4
b0001001011 6
#109
0,
#110
b0001000001 &
b0010111 +
1,
b0000000000010111 4
b0000010111 6
#111
0,
#112
b0001000000 &
b0101111 +
1,
b0000000000101111 4
b0000101111 6
#113
0,
#114
b0000111111 &
b1011111 +
1,
b0000000001011111 4
b0001011111 6
#115
0,
#116
b0000111110 &
b0111110 +
1,
b0000000000111110 4
b0000111110 6
#117
0,
#118
b0000111101 &
b1111101 +
1,
b0000000001111101 4
b0001111101 6
#119
0,
#120
b0000111100 &
b1111010 +
1,
b0000000001111010 4
b0001111010 6
#121
0,
#122
b0000111011 &
b1110101 +
1,
b0000000001110101 4
b0001110101 6
#123
0,
#124
b0000111010 &
b1101010 +
1,
b0000000001101010 4
b0001101010 6
#125
0,
#126
b0000111001 &
b1010101 +
1,
b0000000001010101 4
b0001010101 6
#127
0,
#128
b0000111000 &
b0101010 +
1,
b0000000000101010 4
b0000101010 6
#129
0,
#130
b0000110111 &
b1010100 +
1,
b0000000001010100 4
b0001010100 6
#131
0,
#132
b0000110110 &
b0101000 +
1,
b0000000000101000 4
b0000101000 6
#133
0,
#134
b0000110101 &
b1010000 +
1,
b0000000001010000 4
b0001010000 6
#135
0,
#136
b0000110100 &
b0100001 +
1,
b0000000000100001 4
b0000100001 6
#137
0,
#138
b0000110011 &
b1000010 +
1,
b0000000001000010 4
b0001000010 6
#139
0,
#140
b0000110010 &
b0000101 +
1,
b0000000000000101 4
b0000000101 6
#141
0,
#142
b0000110001 &
b0001011 +
1,
b0000000000001011 4
b0000001011 6
#143
0,
#144
b0000110000 &
b0010110 +
1,
b0000000000010110 4
b0000010110 6
#145
0,
#146
b0000101111 &
b0101101 +
1,
b0000000000101101 4
b0000101101 6
#147
0,
#148
b0000101110 &
b1011011 +
1,
b0000000001011011 4
b0001011011 6
#149
0,
#150
b0000101101 &
b0110111 +
1,
b0000000000110111 4
b0000110111 6
#151
0,
#152
b0000101100 &
b1101111 +
1,
b0000000001101111 4
b0001101111 6
#153
0,
#154
b0000101011 &
b1011110 +
1,
b0000000001011110 4
b0001011110 6
#155
0,
#156
b0000101010 &
b0111100 +
1,
b0000000000111100 4
b0000111100 6
#157
0,
#158
b0000101001 &
b1111001 +
1,
b0000000001111001 4
b0001111001 6
#159
0,
#160
b0000101000 &
b1110011 +
1,
b0000000001110011 4
b0001110011 6
#161
0,
#162
b0000100111 &
b1100111 +
1,
10
b0000000001100111 4
b0001100111 6
#163
0,
#164
b0000100110 &
b00000001 (
b00000000000000000000000000000001 )
b00000000000000000000000000000010 *
b1001110 +
1,
00
b00000001 1
12
b0000000001001110 4
b0001001110 6
#165
0,
#166
b0000000000010111 %
b0000100101 &
b0011100 +
1,
b0000000000011100 4
b0000011100 6
#167
0,
#168
b0000000000010110 %
b0000100100 &
b0111001 +
1,
b0000000000111001 4
b0000111001 6
#169
0,
#170
b0000000000010101 %
b0000100011 &
b1110010 +
1,
b0000000001110010 4
b0001110010 6
#171
0,
#172
b0000000000010100 %
b0000100010 &
b1100101 +
1,
b0000000001100101 4
b0001100101 6
#173
0,
#174
b0000000000010011 %
b0000100001 &
b1001010 +
1,
b0000000001001010 4
b0001001010 6
#175
0,
#176
b0000000000010010 %
b0000100000 &
b0010101 +
1,
b0000000000010101 4
b0000010101 6
#177
0,
#178
b0000000000010001 %
b0000011111 &
b0101011 +
1,
b0000000000101011 4
b0000101011 6
#179
0,
#180
b0000000000010000 %
b0000011110 &
b1010110 +
1,
b0000000001010110 4
b0001010110 6
#181
0,
#182
b0000000000001111 %
b0000011101 &
b0101100 +
1,
b0000000000101100 4
b0000101100 6
#183
0,
#184
b0000000000001110 %
b0000011100 &
b1011001 +
1,
b0000000001011001 4
b0001011001 6
#185
0,
#186
b0000000000001101 %
b0000011011 &
b0110011 +
1,
b0000000000110011 4
b0000110011 6
#187
0,
#188
b0000000000001100 %
b0000011010 &
b1100110 +
1,
b0000000001100110 4
b0001100110 6
#189
0,
#190
b0000000000001011 %
b0000011001 &
b1001100 +
1,
b0000000001001100 4
b0001001100 6
#191
0,
#192
b0000000000001010 %
b0000011000 &
b0011000 +
1,
b0000000000011000 4
b0000011000 6
#193
0,
#194
b0000000000001001 %
b0000010111 &
b0110000 +
1,
b0000000000110000 4
b0000110000 6
#195
0,
#196
b0000000000001000 %
b0000010110 &
b1100000 +
1,
b0000000001100000 4
b0001100000 6
#197
0,
#198
b0000000000000111 %
b0000010101 &
b1000001 +
1,
b0000000001000001 4
b0001000001 6
#199
0,
#200
b0000000000000110 %
b0000010100 &
b0000011 +
1,
b0000000000000011 4
b0000000011 6
#201
0,
#202
b0000000000000101 %
b0000010011 &
b0000110 +
1,
b0000000000000110 4
b0000000110 6
#203
0,
#204
b0000000000000100 %
b0000010010 &
b0001101 +
1,
b0000000000001101 4
b0000001101 6
#205
0,
#206
b0000000000000011 %
b0000010001 &
b0011011 +
1,
b0000000000011011 4
b0000011011 6
#207
0,
#208
b0000000000000010 %
b0000010000 &
b0110110 +
1,
b0000000000110110 4
b0000110110 6
#209
0,
#210
b0000000000000001 %
b0000001111 &
b1101101 +
1,
b0000000001101101 4
b0001101101 6
#211
0,
#212
b0000000000000000 %
b0000001110 &
b1011010 +
1,
b0000000001011010 4
b0001011010 6
#213
0,
#214
1$
b0000000000011000 %
b0000001101 &
b0110101 +
1,
b0000000000110101 4
15
b0000110101 6
#215
0,
#216
0$
b0000000000010111 %
b0000001100 &
b00000011 (
b00000000000000000000000000000010 )
b00000000000000000000000000000011 *
b1101011 +
1,
b00000011 1
b0000000001101011 4
05
b0001101011 6
#217
0,
#218
b0000000000010110 %
b0000001011 &
b1010111 +
1,
b0000000001010111 4
b0001010111 6
#219
0,
#220
b0000000000010101 %
b0000001010 &
b0101110 +
1,
b0000000000101110 4
b0000101110 6
#221
0,
#222
b0000000000010100 %
b0000001001 &
b1011101 +
1,
b0000000001011101 4
b0001011101 6
#223
0,
#224
b0000000000010011 %
b0000001000 &
b0111010 +
1,
b0000000000111010 4
b0000111010 6
#225
0,
#226
b0000000000010010 %
b0000000111 &
b1110100 +
1,
b0000000001110100 4
b0001110100 6
#227
0,
#228
b0000000000010001 %
b0000000110 &
b1101000 +
1,
b0000000001101000 4
b0001101000 6
#229
0,
#230
b0000000000010000 %
b0000000101 &
b1010001 +
1,
b0000000001010001 4
b0001010001 6
#231
0,
#232
b0000000000001111 %
b0000000100 &
b0100011 +
1,
b0000000000100011 4
b0000100011 6
#233
0,
#234
b0000000000001110 %
b0000000011 &
b1000110 +
1,
b0000000001000110 4
b0001000110 6
#235
0,
#236
b0000000000001101 %
b0000000010 &
b0001100 +
1,
b0000000000001100 4
b0000001100 6
#237
0,
#238
b0000000000001100 %
b0000000001 &
b0011001 +
1,
b0000000000011001 4
b0000011001 6
#239
0,
#240
b0000000000001011 %
b0000000000 &
b0110010 +
1,
b0000000000110010 4
b0000110010 6
#241
0,
#242
b0000000000001010 %
b0000110001 &
b1100100 +
1,
b0000000001100100 4
b0001100100 6
#243
0,
#244
b0000000000001001 %
b0000110000 &
b1001000 +
1,
b0000000001001000 4
b0001001000 6
#245
0,
#246
b0000000000001000 %
b0000101111 &
b0010001 +
1,
b0000000000010001 4
b0000010001 6
#247
0,
#248
b0000000000000111 %
b0000101110 &
b0100010 +
1,
b0000000000100010 4
b0000100010 6
#249
0,
#250
b0000000000000110 %
b0000101101 &
b1000100 +
1,
b0000000001000100 4
b0001000100 6
#251
0,
#252
b0000000000000101 %
b0000101100 &
b0001000 +
1,
b0000000000001000 4
b0000001000 6
#253
0,
#254
b0000000000000100 %
b0000101011 &
b0010000 +
1,
b0000000000010000 4
b0000010000 6
#255
0,
#256
b0000000000000011 %
b0000101010 &
b0100000 +
1,
b0000000000100000 4
b0000100000 6
#257
0,
#258
b0000000000000010 %
b0000101001 &
b1000000 +
1,
b0000000001000000 4
b0001000000 6
#259
0,
#260
b0000000000000001 %
b0000101000 &
b0000001 +
1,
b0000000000000001 4
b0000000001 6
#261
0,
#262
b0000000000000000 %
b0000100111 &
b0000010 +
1,
b0000000000000010 4
b0000000010 6
#263
0,
#264
1$
b0000000000011000 %
b0000100110 &
b0000100 +
1,
b0000000000000100 4
15
b0000000100 6
#265
0,
#266
0$
b0000000000010111 %
b0000100101 &
b00000111 (
b00000000000000000000000000000011 )
b00000000000000000000000000000100 *
b0001001 +
1,
b00000111 1
b0000000000001001 4
05
b0000001001 6
#267
0,
#268
b0000000000010110 %
b0000100100 &
b0010010 +
1,
b0000000000010010 4
b0000010010 6
#269
0,
#270
b0000000000010101 %
b0000100011 &
b0100100 +
1,
b0000000000100100 4
b0000100100 6
#271
0,
#272
b0000000000010100 %
b0000100010 &
b1001001 +
1,
b0000000001001001 4
b0001001001 6
#273
0,
#274
b0000000000010011 %
b0000100001 &
b0010011 +
1,
b0000000000010011 4
b0000010011 6
#275
0,
#276
b0000000000010010 %
b0000100000 &
b0100110 +
1,
b0000000000100110 4
b0000100110 6
#277
0,
#278
b0000000000010001 %
b0000011111 &
b1001101 +
1,
b0000000001001101 4
b0001001101 6
#279
0,
#280
b0000000000010000 %
b0000011110 &
b0011010 +
1,
b0000000000011010 4
b0000011010 6
#281
0,
#282
b0000000000001111 %
b0000011101 &
b0110100 +
1,
b0000000000110100 4
b0000110100 6
#283
0,
#284
b0000000000001110 %
b0000011100 &
b1101001 +
1,
b0000000001101001 4
b0001101001 6
#285
0,
#286
b0000000000001101 %
b0000011011 &
b1010011 +
1,
b0000000001010011 4
b0001010011 6
#287
0,
#288
b0000000000001100 %
b0000011010 &
b0100111 +
1,
b0000000000100111 4
b0000100111 6
#289
0,
#290
b0000000000001011 %
b0000011001 &
b1001111 +
1,
b0000000001001111 4
b0001001111 6
#291
0,
#292
b0000000000001010 %
b0000011000 &
b0011110 +
1,
b0000000000011110 4
b0000011110 6
#293
0,
#294
b0000000000001001 %
b0000010111 &
b0111101 +
1,
b0000000000111101 4
b0000111101 6
#295
0,
#296
b0000000000001000 %
b0000010110 &
b1111011 +
1,
b0000000001111011 4
b0001111011 6
#297
0,
#298
b0000000000000111 %
b0000010101 &
b1110111 +
1,
b0000000001110111 4
b0001110111 6
#299
0,
#300
b0000000000000110 %
b0000010100 &
b1101110 +
1,
b0000000001101110 4
b0001101110 6
#301
0,
#302
b0000000000000101 %
b0000010011 &
b1011100 +
1,
b0000000001011100 4
b0001011100 6
#303
0,
#304
b0000000000000100 %
b0000010010 &
b0111000 +
1,
b0000000000111000 4
b0000111000 6
#305
0,
#306
b0000000000000011 %
b0000010001 &
b1110000 +
1,
b0000000001110000 4
b0001110000 6
#307
0,
#308
b0000000000000010 %
b0000010000 &
b1100001 +
1,
b0000000001100001 4
b0001100001 6
#309
0,
#310
b0000000000000001 %
b0000001111 &
b1000011 +
1,
b0000000001000011 4
b0001000011 6
#311
0,
#312
b0000000000000000 %
b0000001110 &
b0000111 +
1,
b0000000000000111 4
b0000000111 6
#313
0,
#314
1$
b0000000000011000 %
b0000001101 &
b0001111 +
1,
b0000000000001111 4
15
b0000001111 6
#315
0,
#316
0$
b0000000000010111 %
b0000001100 &
b00001111 (
b00000000000000000000000000000100 )
b00000000000000000000000000000101 *
b0011111 +
1,
b00001111 1
b0000000000011111 4
05
b0000011111 6
#317
0,
#318
b0000000000010110 %
b0000001011 &
b0111111 +
1,
b0000000000111111 4
b0000111111 6
#319
0,
#320
b0000000000010101 %
b0000001010 &
b1111111 +
1,
b0000000001111111 4
b0001111111 6
#321
0,
#322
b0000000000010100 %
b0000001001 &
b1111110 +
1,
b0000000001111110 4
b0001111110 6
#323
0,
#324
b0000000000010011 %
b0000001000 &
b1111100 +
1,
b0000000001111100 4
b0001111100 6
#325
0,
#326
b0000000000010010 %
b0000000111 &
b1111000 +
1,
b0000000001111000 4
b0001111000 6
#327
0,
#328
b0000000000010001 %
b0000000110 &
b1110001 +
1,
b0000000001110001 4
b0001110001 6
#329
0,
#330
b0000000000010000 %
b0000000101 &
b1100011 +
1,
b0000000001100011 4
b0001100011 6
#331
0,
#332
b0000000000001111 %
b0000000100 &
b1000111 +
1,
b0000000001000111 4
b0001000111 6
#333
0,
#334
b0000000000001110 %
b0000000011 &
b0001110 +
1,
b0000000000001110 4
b0000001110 6
#335
0,
#336
b0000000000001101 %
b0000000010 &
b0011101 +
1,
b0000000000011101 4
b0000011101 6
#337
0,
#338
b0000000000001100 %
b0000000001 &
b0111011 +
1,
b0000000000111011 4
b0000111011 6
#339
0,
#340
b0000000000001011 %
b0000000000 &
b1110110 +
1,
b0000000001110110 4
b0001110110 6
#341
0,
#342
b0000000000001010 %
b0001110101 &
b1101100 +
1,
b0000000001101100 4
b0001101100 6
#343
0,
#344
b0000000000001001 %
b0001110100 &
b1011000 +
1,
b0000000001011000 4
b0001011000 6
#345
0,
#346
b0000000000001000 %
b0001110011 &
b0110001 +
1,
b0000000000110001 4
b0000110001 6
#347
0,
#348
b0000000000000111 %
b0001110010 &
b1100010 +
1,
b0000000001100010 4
b0001100010 6
#349
0,
#350
b0000000000000110 %
b0001110001 &
b1000101 +
1,
b0000000001000101 4
b0001000101 6
#351
0,
#352
b0000000000000101 %
b0001110000 &
b0001010 +
1,
b0000000000001010 4
b0000001010 6
#353
0,
#354
b0000000000000100 %
b0001101111 &
b0010100 +
1,
b0000000000010100 4
b0000010100 6
#355
0,
#356
b0000000000000011 %
b0001101110 &
b0101001 +
1,
b0000000000101001 4
b0000101001 6
#357
0,
#358
b0000000000000010 %
b0001101101 &
b1010010 +
1,
b0000000001010010 4
b0001010010 6
#359
0,
#360
b0000000000000001 %
b0001101100 &
b0100101 +
1,
b0000000000100101 4
b0000100101 6
#361
0,
#362
b0000000000000000 %
b0001101011 &
b1001011 +
1,
b0000000001001011 4
b0001001011 6
#363
0,
#364
1$
b0000000000011000 %
b0001101010 &
b0010111 +
1,
b0000000000010111 4
15
b0000010111 6
#365
0,
#366
0$
b0000000000010111 %
b0001101001 &
b00011111 (
b00000000000000000000000000000101 )
b00000000000000000000000000000110 *
b0101111 +
1,
b00011111 1
b0000000000101111 4
05
b0000101111 6
#367
0,
#368
b0000000000010110 %
b0001101000 &
b1011111 +
1,
b0000000001011111 4
b0001011111 6
#369
0,
#370
b0000000000010101 %
b0001100111 &
b0111110 +
1,
b0000000000111110 4
b0000111110 6
#371
0,
#372
b0000000000010100 %
b0001100110 &
b1111101 +
1,
b0000000001111101 4
b0001111101 6
#373
0,
#374
b0000000000010011 %
b0001100101 &
b1111010 +
1,
b0000000001111010 4
b0001111010 6
#375
0,
#376
b0000000000010010 %
b0001100100 &
b1110101 +
1,
b0000000001110101 4
b0001110101 6
#377
0,
#378
b0000000000010001 %
b0001100011 &
b1101010 +
1,
b0000000001101010 4
b0001101010 6
#379
0,
#380
b0000000000010000 %
b0001100010 &
b1010101 +
1,
b0000000001010101 4
b0001010101 6
#381
0,
#382
b0000000000001111 %
b0001100001 &
b0101010 +
1,
b0000000000101010 4
b0000101010 6
#383
0,
#384
b0000000000001110 %
b0001100000 &
b1010100 +
1,
b0000000001010100 4
b0001010100 6
#385
0,
#386
b0000000000001101 %
b0001011111 &
b0101000 +
1,
b0000000000101000 4
b0000101000 6
#387
0,
#388
b0000000000001100 %
b0001011110 &
b1010000 +
1,
b0000000001010000 4
b0001010000 6
#389
0,
#390
b0000000000001011 %
b0001011101 &
b0100001 +
1,
b0000000000100001 4
b0000100001 6
#391
0,
#392
b0000000000001010 %
b0001011100 &
b1000010 +
1,
b0000000001000010 4
b0001000010 6
#393
0,
#394
b0000000000001001 %
b0001011011 &
b0000101 +
1,
b0000000000000101 4
b0000000101 6
#395
0,
#396
b0000000000001000 %
b0001011010 &
b0001011 +
1,
b0000000000001011 4
b0000001011 6
#397
0,
#398
b0000000000000111 %
b0001011001 &
b0010110 +
1,
b0000000000010110 4
b0000010110 6
#399
0,
#400
b0000000000000110 %
b0001011000 &
b0101101 +
1,
b0000000000101101 4
b0000101101 6
#401
0,
#402
b0000000000000101 %
b0001010111 &
b1011011 +
1,
b0000000001011011 4
b0001011011 6
#403
0,
#404
b0000000000000100 %
b0001010110 &
b0110111 +
1,
b0000000000110111 4
b0000110111 6
#405
0,
#406
b0000000000000011 %
b0001010101 &
b1101111 +
1,
b0000000001101111 4
b0001101111 6
#407
0,
#408
b0000000000000010 %
b0001010100 &
b1011110 +
1,
b0000000001011110 4
b0001011110 6
#409
0,
#410
b0000000000000001 %
b0001010011 &
b0111100 +
1,
b0000000000111100 4
b0000111100 6
#411
0,
#412
b0000000000000000 %
b0001010010 &
b1111001 +
1,
b0000000001111001 4
b0001111001 6
#413
0,
#414
1$
b0000000000011000 %
b0001010001 &
b1110011 +
1,
b0000000001110011 4
15
b0001110011 6
#415
0,
#416
0$
b0000000000010111 %
b0001010000 &
b00111111 (
b00000000000000000000000000000110 )
b00000000000000000000000000000111 *
b1100111 +
1,
b00111111 1
b0000000001100111 4
05
b0001100111 6
#417
0,
#418
b0000000000010110 %
b0001001111 &
b1001110 +
1,
b0000000001001110 4
b0001001110 6
#419
0,
#420
b0000000000010101 %
b0001001110 &
b0011100 +
1,
b0000000000011100 4
b0000011100 6
#421
0,
#422
b0000000000010100 %
b0001001101 &
b0111001 +
1,
b0000000000111001 4
b0000111001 6
#423
0,
#424
b0000000000010011 %
b0001001100 &
b1110010 +
1,
b0000000001110010 4
b0001110010 6
#425
0,
#426
b0000000000010010 %
b0001001011 &
b1100101 +
1,
b0000000001100101 4
b0001100101 6
#427
0,
#428
b0000000000010001 %
b0001001010 &
b1001010 +
1,
b0000000001001010 4
b0001001010 6
#429
0,
